{"nodes": [{"count": 5924, "lender": "JP Morgan Chase", "purpose": "CASH-OUT REFINANCE", "d_count": 393, "i": 0, "dr": 0.0663, "id": "010d8e6be0802699379a7b332072ecfd18bede01", "channel": "RETAIL"}, {"count": 718, "lender": "JP Morgan Chase", "purpose": "PURCHASE", "d_count": 46, "i": 1, "dr": 0.0641, "id": "01121e0e5f5db6366fc828df8be8a863ea760598", "channel": "BROKER"}, {"count": 1851, "lender": "Flagstar Bank", "purpose": "CASH-OUT REFINANCE", "d_count": 187, "i": 2, "dr": 0.101, "id": "03ac6357f2a67b30ceb6df24122902783dc268c1", "channel": "CORRESPONDENT"}, {"count": 770, "lender": "Bishop's Gate Mortgage", "purpose": "PURCHASE", "d_count": 37, "i": 3, "dr": 0.0481, "id": "0517ccd30343207bc0edc1b3a8863c76daba8743", "channel": "RETAIL"}, {"count": 1712, "lender": "First Horizon National", "purpose": "OTHER REFINANCE", "d_count": 111, "i": 4, "dr": 0.0648, "id": "061bd47cf11f1b18c389ad8997d4cee1ae73bd26", "channel": "RETAIL"}, {"count": 488, "lender": "AmTrust", "purpose": "CASH-OUT REFINANCE", "d_count": 46, "i": 5, "dr": 0.0943, "id": "0869df85a08d0361441b4755fa33bfa939916bf5", "channel": "BROKER"}, {"count": 2298, "lender": "Bank of America", "purpose": "OTHER REFINANCE", "d_count": 245, "i": 6, "dr": 0.1066, "id": "12c296d6c92b905a8c7690b4b8fef2d98cfa1f76", "channel": "RETAIL"}, {"count": 2938, "lender": "Bank of America", "purpose": "PURCHASE", "d_count": 273, "i": 7, "dr": 0.0929, "id": "12f6dfea8643f792b6918041bba4d0f1b7130b6f", "channel": "BROKER"}, {"count": 1023, "lender": "USAA", "purpose": "CASH-OUT REFINANCE", "d_count": 46, "i": 8, "dr": 0.045, "id": "17341a05b765880ab91d3cebe4b03ea152badf2f", "channel": "RETAIL"}, {"count": 946, "lender": "Suntrust", "purpose": "CASH-OUT REFINANCE", "d_count": 63, "i": 9, "dr": 0.0666, "id": "1e1792bc5ccaaa0976ffac7f9baa5a8cd385f5bd", "channel": "CORRESPONDENT"}, {"count": 6069, "lender": "JP Morgan Chase", "purpose": "PURCHASE", "d_count": 415, "i": 10, "dr": 0.0684, "id": "27746114f2563334b1134c5327e58ef4b3f30db7", "channel": "RETAIL"}, {"count": 10250, "lender": "Bank of America", "purpose": "PURCHASE", "d_count": 801, "i": 11, "dr": 0.0781, "id": "2b786e372f352d39bff37dbe33c7e9002500ddf1", "channel": "CORRESPONDENT"}, {"count": 3257, "lender": "PNC", "purpose": "PURCHASE", "d_count": 211, "i": 12, "dr": 0.0648, "id": "2c70343de6c7cfd6b70dd1c9f0d1ac91681d6a61", "channel": "RETAIL"}, {"count": 299, "lender": "Regions", "purpose": "PURCHASE", "d_count": 12, "i": 13, "dr": 0.0401, "id": "2df2bd38d0f73de0c14c6153f6d62dc9f4dd7740", "channel": "BROKER"}, {"count": 1367, "lender": "AmTrust", "purpose": "CASH-OUT REFINANCE", "d_count": 121, "i": 14, "dr": 0.0885, "id": "2e771a434b1edfd7e504597b3b6fdbebe68c444f", "channel": "CORRESPONDENT"}, {"count": 682, "lender": "USAA", "purpose": "OTHER REFINANCE", "d_count": 21, "i": 15, "dr": 0.0308, "id": "2fa2d23f196fcad0f8978d98d6de14cc9025f613", "channel": "RETAIL"}, {"count": 1433, "lender": "ABN AMRO", "purpose": "CASH-OUT REFINANCE", "d_count": 110, "i": 16, "dr": 0.0768, "id": "346de3c6851ce95b118db29a96c841240fffddac", "channel": "RETAIL"}, {"count": 11670, "lender": "Wells Fargo", "purpose": "OTHER REFINANCE", "d_count": 568, "i": 17, "dr": 0.0487, "id": "3693a118e3ad6a9a6d5c16d86a401d76024e1835", "channel": "RETAIL"}, {"count": 2053, "lender": "GMAC", "purpose": "PURCHASE", "d_count": 98, "i": 18, "dr": 0.0477, "id": "371d855af1cf3fd044d657a67472e0dcf29d05df", "channel": "RETAIL"}, {"count": 1012, "lender": "Suntrust", "purpose": "PURCHASE", "d_count": 70, "i": 19, "dr": 0.0692, "id": "399f32094c42a6c6d76ff29f76c543e059908a36", "channel": "BROKER"}, {"count": 2378, "lender": "GMAC", "purpose": "PURCHASE", "d_count": 97, "i": 20, "dr": 0.0408, "id": "3a8cd56582137d7f435230d69b25c9ab9ef28c5f", "channel": "CORRESPONDENT"}, {"count": 1971, "lender": "First Horizon National", "purpose": "PURCHASE", "d_count": 98, "i": 21, "dr": 0.0497, "id": "3bfe2cecc9b024cec66131b89a04977aa869c970", "channel": "RETAIL"}, {"count": 698, "lender": "Flagstar Bank", "purpose": "OTHER REFINANCE", "d_count": 59, "i": 22, "dr": 0.0845, "id": "3cb08dafcc3b3744df6d06eaeb01dc8840153354", "channel": "CORRESPONDENT"}, {"count": 1959, "lender": "Citi", "purpose": "CASH-OUT REFINANCE", "d_count": 125, "i": 23, "dr": 0.0638, "id": "3e3fb9bd1df92c04abf362f8916d8fcca5ad7e56", "channel": "RETAIL"}, {"count": 2556, "lender": "USAA", "purpose": "PURCHASE", "d_count": 61, "i": 24, "dr": 0.0239, "id": "42dcc20d973f096aca5f98e31dfcaa79751da17d", "channel": "RETAIL"}, {"count": 1854, "lender": "Wells Fargo", "purpose": "CASH-OUT REFINANCE", "d_count": 142, "i": 25, "dr": 0.0766, "id": "431496650d2aea9074f5e8fa473df4d367d9550a", "channel": "CORRESPONDENT"}, {"count": 989, "lender": "Flagstar Bank", "purpose": "OTHER REFINANCE", "d_count": 96, "i": 26, "dr": 0.0971, "id": "4653e080c51a6df17384feec3c1ca41d8aced275", "channel": "BROKER"}, {"count": 987, "lender": "Wells Fargo", "purpose": "OTHER REFINANCE", "d_count": 58, "i": 27, "dr": 0.0588, "id": "4701fa7c18b319783c2e13e58cc519c50217fb20", "channel": "CORRESPONDENT"}, {"count": 997, "lender": "Suntrust", "purpose": "CASH-OUT REFINANCE", "d_count": 76, "i": 28, "dr": 0.0762, "id": "47022560c1cddb57bce2e24b946b50ab0dd21563", "channel": "RETAIL"}, {"count": 6281, "lender": "Citi", "purpose": "PURCHASE", "d_count": 349, "i": 29, "dr": 0.0556, "id": "500448e180ec43d5cc05ef80d513e8841c72bfd1", "channel": "CORRESPONDENT"}, {"count": 538, "lender": "Suntrust", "purpose": "OTHER REFINANCE", "d_count": 29, "i": 30, "dr": 0.0539, "id": "504842b54b954efd4a7958b52e4a827b26579696", "channel": "BROKER"}, {"count": 5156, "lender": "JP Morgan Chase", "purpose": "OTHER REFINANCE", "d_count": 335, "i": 31, "dr": 0.065, "id": "5258aadf83d2ee8875fdca903f5dd447aa68d04c", "channel": "CORRESPONDENT"}, {"count": 1290, "lender": "Suntrust", "purpose": "CASH-OUT REFINANCE", "d_count": 92, "i": 32, "dr": 0.0713, "id": "61b6d810d7d9727a8fc4f413e7073d3c6a67bd4a", "channel": "BROKER"}, {"count": 1567, "lender": "First Horizon National", "purpose": "CASH-OUT REFINANCE", "d_count": 128, "i": 33, "dr": 0.0817, "id": "62843fe90d493a621d0704243b68f3df39e0a08d", "channel": "RETAIL"}, {"count": 277, "lender": "Flagstar Bank", "purpose": "CASH-OUT REFINANCE", "d_count": 36, "i": 34, "dr": 0.13, "id": "62ea720f6804e662b28cac5e8e44489d0fbea6d5", "channel": "RETAIL"}, {"count": 5011, "lender": "Citi", "purpose": "CASH-OUT REFINANCE", "d_count": 464, "i": 35, "dr": 0.0926, "id": "68a2d1d03a6cd162645475c0fd7be6c36aa41e37", "channel": "CORRESPONDENT"}, {"count": 2523, "lender": "Bank of America", "purpose": "OTHER REFINANCE", "d_count": 315, "i": 36, "dr": 0.1249, "id": "6ec815f20dfc53bfc773bd81ebb9a9ee1fbafe8a", "channel": "BROKER"}, {"count": 757, "lender": "Citi", "purpose": "OTHER REFINANCE", "d_count": 44, "i": 37, "dr": 0.0581, "id": "6f243cbe3b728031f9a1fd0ee4dae2a7cebde078", "channel": "BROKER"}, {"count": 2319, "lender": "GMAC", "purpose": "OTHER REFINANCE", "d_count": 134, "i": 38, "dr": 0.0578, "id": "7070950fa8479ed0c1e6aa991b9272ffea5bbce6", "channel": "RETAIL"}, {"count": 937, "lender": "Irwin Mortgage", "purpose": "PURCHASE", "d_count": 41, "i": 39, "dr": 0.0438, "id": "769938518885163b6d96203e4e7daea64e6fb644", "channel": "CORRESPONDENT"}, {"count": 296, "lender": "Irwin Mortgage", "purpose": "PURCHASE", "d_count": 20, "i": 40, "dr": 0.0676, "id": "7fceccdbe5efe751bcae10f1054b59a2b881cafb", "channel": "RETAIL"}, {"count": 2328, "lender": "Citi", "purpose": "OTHER REFINANCE", "d_count": 122, "i": 41, "dr": 0.0524, "id": "7fd725f53df481934fa4a17d062afac1c4555736", "channel": "CORRESPONDENT"}, {"count": 1177, "lender": "Flagstar Bank", "purpose": "PURCHASE", "d_count": 96, "i": 42, "dr": 0.0816, "id": "82d9a4d7043778612801119fd45fd9ad141ef6aa", "channel": "CORRESPONDENT"}, {"count": 6282, "lender": "GMAC", "purpose": "CASH-OUT REFINANCE", "d_count": 481, "i": 43, "dr": 0.0766, "id": "84e67b37698b696f6315d1c43fb21c290a6dfe5f", "channel": "RETAIL"}, {"count": 1508, "lender": "Regions", "purpose": "CASH-OUT REFINANCE", "d_count": 134, "i": 44, "dr": 0.0889, "id": "8787e27ccbe344409d51aeaf73d25fa2a8a7ba0f", "channel": "RETAIL"}, {"count": 665, "lender": "Suntrust", "purpose": "OTHER REFINANCE", "d_count": 26, "i": 45, "dr": 0.0391, "id": "87a2ccbb70b0de0eab943fecd2f72bf4f7a69d77", "channel": "CORRESPONDENT"}, {"count": 4815, "lender": "Bank of America", "purpose": "CASH-OUT REFINANCE", "d_count": 572, "i": 46, "dr": 0.1188, "id": "8a4d4e5b2ec8d5ca71adb6e6e41d419cd4ff1851", "channel": "RETAIL"}, {"count": 628, "lender": "Irwin Mortgage", "purpose": "CASH-OUT REFINANCE", "d_count": 52, "i": 47, "dr": 0.0828, "id": "8e507842ab0a543c64aaefe66c59726b0c3f6e5e", "channel": "CORRESPONDENT"}, {"count": 1198, "lender": "Citi", "purpose": "CASH-OUT REFINANCE", "d_count": 99, "i": 48, "dr": 0.0826, "id": "92b99d6e8274dd7b62eec83cee9b7537a6c1d6de", "channel": "BROKER"}, {"count": 300, "lender": "Irwin Mortgage", "purpose": "CASH-OUT REFINANCE", "d_count": 28, "i": 49, "dr": 0.0933, "id": "9435fe4d1dc0b2c208ba2c4d7294ebb4c38e7616", "channel": "RETAIL"}, {"count": 632, "lender": "Irwin Mortgage", "purpose": "CASH-OUT REFINANCE", "d_count": 76, "i": 50, "dr": 0.1203, "id": "954421b36660568919d3370eda929ac242ef99b8", "channel": "BROKER"}, {"count": 12164, "lender": "Wells Fargo", "purpose": "CASH-OUT REFINANCE", "d_count": 781, "i": 51, "dr": 0.0642, "id": "958b2e78d362ed427bced0bc49f27a5dfd1428a2", "channel": "RETAIL"}, {"count": 2411, "lender": "PNC", "purpose": "OTHER REFINANCE", "d_count": 169, "i": 52, "dr": 0.0701, "id": "980e4a7f5bc66aa9313539f67da6d2950ef64538", "channel": "RETAIL"}, {"count": 17316, "lender": "Wells Fargo", "purpose": "PURCHASE", "d_count": 975, "i": 53, "dr": 0.0563, "id": "98408b29d5a8921fa19695f30a6067d6bf9911ae", "channel": "RETAIL"}, {"count": 2138, "lender": "PNC", "purpose": "CASH-OUT REFINANCE", "d_count": 214, "i": 54, "dr": 0.1001, "id": "98d92aa7251249089eb1e12fbfb65f51a361a3e8", "channel": "RETAIL"}, {"count": 2243, "lender": "Wells Fargo", "purpose": "PURCHASE", "d_count": 94, "i": 55, "dr": 0.0419, "id": "9c3447fa710754a9c34d4500f6ef7146625c1da5", "channel": "CORRESPONDENT"}, {"count": 498, "lender": "Irwin Mortgage", "purpose": "PURCHASE", "d_count": 46, "i": 56, "dr": 0.0924, "id": "9fe69cee7669076a6eeb9629b458dd8977b48ac9", "channel": "BROKER"}, {"count": 7875, "lender": "Bank of America", "purpose": "CASH-OUT REFINANCE", "d_count": 804, "i": 57, "dr": 0.1021, "id": "aad3f81dc4fe3acef405823a27429a4bef752141", "channel": "CORRESPONDENT"}, {"count": 6696, "lender": "JP Morgan Chase", "purpose": "PURCHASE", "d_count": 384, "i": 58, "dr": 0.0573, "id": "acf170f52801ae928c54adfb029526e9035b0703", "channel": "CORRESPONDENT"}, {"count": 834, "lender": "Fifth Third Bank", "purpose": "CASH-OUT REFINANCE", "d_count": 62, "i": 59, "dr": 0.0743, "id": "ad99454f651195af8d56504738938999326ee4d6", "channel": "RETAIL"}, {"count": 6402, "lender": "Bank of America", "purpose": "OTHER REFINANCE", "d_count": 567, "i": 60, "dr": 0.0886, "id": "adb2171de290e3ae5d681be4962e675e12b70353", "channel": "CORRESPONDENT"}, {"count": 557, "lender": "JP Morgan Chase", "purpose": "OTHER REFINANCE", "d_count": 39, "i": 61, "dr": 0.07, "id": "ae63d535e0c85233df794e98d9dd03403a0049eb", "channel": "BROKER"}, {"count": 398, "lender": "Bishop's Gate Mortgage", "purpose": "PURCHASE", "d_count": 24, "i": 62, "dr": 0.0603, "id": "b17612fd36e4c154fb5c8255f6c52a3259287c3f", "channel": "BROKER"}, {"count": 2757, "lender": "AmTrust", "purpose": "PURCHASE", "d_count": 165, "i": 63, "dr": 0.0598, "id": "b4606c45a7040f9800ac9fb6284c3e59b60df1b9", "channel": "CORRESPONDENT"}, {"count": 784, "lender": "Irwin Mortgage", "purpose": "OTHER REFINANCE", "d_count": 37, "i": 64, "dr": 0.0472, "id": "b4d587263a906c3b16a2bcdf12084e31f8cef288", "channel": "CORRESPONDENT"}, {"count": 1388, "lender": "ABN AMRO", "purpose": "OTHER REFINANCE", "d_count": 112, "i": 65, "dr": 0.0807, "id": "b59c3f263dd7aadb2659879b9a185bb425ac3579", "channel": "RETAIL"}, {"count": 360, "lender": "Flagstar Bank", "purpose": "PURCHASE", "d_count": 34, "i": 66, "dr": 0.0944, "id": "b7b61f7390f71a02f7559719c37dc61f85a6774e", "channel": "RETAIL"}, {"count": 4252, "lender": "Bank of America", "purpose": "PURCHASE", "d_count": 485, "i": 67, "dr": 0.1141, "id": "b7d6943c994274e70251806e7ec2b6659ec76c85", "channel": "RETAIL"}, {"count": 290, "lender": "Wells Fargo", "purpose": "CASH-OUT REFINANCE", "d_count": 33, "i": 68, "dr": 0.1138, "id": "bc3242500875648fb04e015cf5569dcce8253bd7", "channel": "BROKER"}, {"count": 958, "lender": "AmTrust", "purpose": "OTHER REFINANCE", "d_count": 60, "i": 69, "dr": 0.0626, "id": "bcc80a1f624a903a7cbe38db3f7f577a7ce09abe", "channel": "CORRESPONDENT"}, {"count": 1854, "lender": "US Bank", "purpose": "PURCHASE", "d_count": 87, "i": 70, "dr": 0.0469, "id": "c701601bcf5d112aadf7d81d6a62371b0b51bb38", "channel": "RETAIL"}, {"count": 1464, "lender": "Fifth Third Bank", "purpose": "PURCHASE", "d_count": 65, "i": 71, "dr": 0.0444, "id": "c762c86633e2dc109448ea8cbada742a7bdd7809", "channel": "RETAIL"}, {"count": 9548, "lender": "JP Morgan Chase", "purpose": "OTHER REFINANCE", "d_count": 701, "i": 72, "dr": 0.0734, "id": "c7f4efe6c6c0be0502475f74fc0664cf52d65c66", "channel": "RETAIL"}, {"count": 1762, "lender": "US Bank", "purpose": "CASH-OUT REFINANCE", "d_count": 117, "i": 73, "dr": 0.0664, "id": "c963dbe1dc73465871aca4856d777d7a1586def7", "channel": "RETAIL"}, {"count": 1287, "lender": "US Bank", "purpose": "OTHER REFINANCE", "d_count": 65, "i": 74, "dr": 0.0505, "id": "ca3498d0ef580b8155b2e95169c4c7e2a7f3b7d0", "channel": "RETAIL"}, {"count": 1648, "lender": "Regions", "purpose": "PURCHASE", "d_count": 97, "i": 75, "dr": 0.0589, "id": "cd8c9c2fa2da09fa846d81e60b96f765da91ac06", "channel": "RETAIL"}, {"count": 3520, "lender": "Bank of America", "purpose": "CASH-OUT REFINANCE", "d_count": 443, "i": 76, "dr": 0.1259, "id": "cd9debee50defb59c487e8d689e51513dce406e7", "channel": "BROKER"}, {"count": 781, "lender": "Citi", "purpose": "PURCHASE", "d_count": 54, "i": 77, "dr": 0.0691, "id": "cf5ec354048c63b0f2e068810bf5d237c5cf3f81", "channel": "RETAIL"}, {"count": 2726, "lender": "Flagstar Bank", "purpose": "CASH-OUT REFINANCE", "d_count": 330, "i": 78, "dr": 0.1211, "id": "cfbaa7a1afe0b0e47691b0f7015b27c13ffda818", "channel": "BROKER"}, {"count": 422, "lender": "Bishop's Gate Mortgage", "purpose": "PURCHASE", "d_count": 15, "i": 79, "dr": 0.0355, "id": "d1c14e187a89e71f5f7b9a13bf401fe02560c070", "channel": "CORRESPONDENT"}, {"count": 2060, "lender": "Flagstar Bank", "purpose": "PURCHASE", "d_count": 183, "i": 80, "dr": 0.0888, "id": "dbbf60ae0a729c7ad81e960bd5aa13812f166f69", "channel": "BROKER"}, {"count": 1841, "lender": "GMAC", "purpose": "OTHER REFINANCE", "d_count": 85, "i": 81, "dr": 0.0462, "id": "dd6b9cea0ef21c6a9512f235e267ba1b750896af", "channel": "CORRESPONDENT"}, {"count": 1019, "lender": "Regions", "purpose": "OTHER REFINANCE", "d_count": 57, "i": 82, "dr": 0.0559, "id": "e1476329679529ccc9d7adfd0bfe8d9588afa800", "channel": "RETAIL"}, {"count": 381, "lender": "Irwin Mortgage", "purpose": "OTHER REFINANCE", "d_count": 33, "i": 83, "dr": 0.0866, "id": "e43f56e8fb71d5c0df7e5e29cebe42a4620eb1ac", "channel": "BROKER"}, {"count": 1017, "lender": "Citi", "purpose": "OTHER REFINANCE", "d_count": 63, "i": 84, "dr": 0.0619, "id": "e532507f86a23da0130dd835489cd2e1a44b1184", "channel": "RETAIL"}, {"count": 5711, "lender": "JP Morgan Chase", "purpose": "CASH-OUT REFINANCE", "d_count": 501, "i": 85, "dr": 0.0877, "id": "e5c63e71dbca62dd44e08bd3b2a76966e69ff7de", "channel": "CORRESPONDENT"}, {"count": 352, "lender": "Wells Fargo", "purpose": "PURCHASE", "d_count": 27, "i": 86, "dr": 0.0767, "id": "e6d1779218cef1617e96c20cf32644bd16af17a0", "channel": "BROKER"}, {"count": 1447, "lender": "Citi", "purpose": "PURCHASE", "d_count": 95, "i": 87, "dr": 0.0657, "id": "e7516d1dc5b4d3b71d8973a583868726a892370a", "channel": "BROKER"}, {"count": 948, "lender": "ABN AMRO", "purpose": "PURCHASE", "d_count": 91, "i": 88, "dr": 0.096, "id": "e7fe79584b96ffe3b3dd61ec2c060c37a956795f", "channel": "RETAIL"}, {"count": 916, "lender": "JP Morgan Chase", "purpose": "CASH-OUT REFINANCE", "d_count": 78, "i": 89, "dr": 0.0852, "id": "f3123aae27eb583d7493e3fa50e4f65103d3f681", "channel": "BROKER"}, {"count": 1450, "lender": "Suntrust", "purpose": "PURCHASE", "d_count": 88, "i": 90, "dr": 0.0607, "id": "f36a59014e046b3d1cfe660533fff6e69256793f", "channel": "RETAIL"}, {"count": 1147, "lender": "Suntrust", "purpose": "PURCHASE", "d_count": 58, "i": 91, "dr": 0.0506, "id": "f5cf893fea7dac5d2b73ba0ac82c51f25783211a", "channel": "CORRESPONDENT"}, {"count": 323, "lender": "Suntrust", "purpose": "OTHER REFINANCE", "d_count": 13, "i": 92, "dr": 0.0402, "id": "fb47ada1b153971e627947e83e700e5dbf334cc8", "channel": "RETAIL"}, {"count": 775, "lender": "Fifth Third Bank", "purpose": "OTHER REFINANCE", "d_count": 48, "i": 93, "dr": 0.0619, "id": "fd33f892314037de8b2f11fe4a528e1e6c2aa905", "channel": "RETAIL"}, {"count": 263, "lender": "Bishop's Gate Mortgage", "purpose": "CASH-OUT REFINANCE", "d_count": 15, "i": 94, "dr": 0.057, "id": "ff0ec235f161de55eee288b6a9a2bd8272050ec9", "channel": "CORRESPONDENT"}, {"count": 3881, "lender": "GMAC", "purpose": "CASH-OUT REFINANCE", "d_count": 248, "i": 95, "dr": 0.0639, "id": "ff58836c58d877343ea0a16fb186cd736269407a", "channel": "CORRESPONDENT"}], "meta": {"quarter": 1, "top_n": 5, "year": 2005}, "links": [{"source": 31, "isCrit": true, "target": 85, "similarity": 0.957460094561875}, {"source": 31, "isCrit": true, "target": 58, "similarity": 0.899031493689773}, {"source": 31, "isCrit": false, "target": 64, "similarity": 0.733741275371369}, {"source": 31, "isCrit": false, "target": 17, "similarity": 0.732311363825549}, {"source": 31, "isCrit": false, "target": 78, "similarity": 0.727526947404823}, {"source": 50, "isCrit": true, "target": 78, "similarity": 0.885166015911932}, {"source": 50, "isCrit": false, "target": 35, "similarity": 0.876351668228339}, {"source": 50, "isCrit": false, "target": 44, "similarity": 0.874637832550937}, {"source": 50, "isCrit": false, "target": 2, "similarity": 0.871138013182024}, {"source": 50, "isCrit": false, "target": 14, "similarity": 0.871008928052355}, {"source": 54, "isCrit": true, "target": 76, "similarity": 0.960301573009194}, {"source": 54, "isCrit": false, "target": 33, "similarity": 0.943639794702702}, {"source": 54, "isCrit": false, "target": 57, "similarity": 0.937446022966703}, {"source": 54, "isCrit": false, "target": 78, "similarity": 0.935765092474935}, {"source": 54, "isCrit": false, "target": 2, "similarity": 0.931002668976698}, {"source": 54, "isCrit": true, "target": 34, "similarity": 0.829684350908428}, {"source": 54, "isCrit": true, "target": 68, "similarity": 0.827662241591875}, {"source": 87, "isCrit": true, "target": 53, "similarity": 0.938237421018231}, {"source": 87, "isCrit": false, "target": 29, "similarity": 0.938132030126731}, {"source": 87, "isCrit": false, "target": 10, "similarity": 0.934249156751548}, {"source": 87, "isCrit": false, "target": 63, "similarity": 0.929423504946092}, {"source": 87, "isCrit": false, "target": 11, "similarity": 0.928129796789156}, {"source": 41, "isCrit": true, "target": 60, "similarity": 0.949279418203958}, {"source": 41, "isCrit": true, "target": 17, "similarity": 0.930906441694013}, {"source": 41, "isCrit": false, "target": 52, "similarity": 0.930846528678169}, {"source": 41, "isCrit": false, "target": 38, "similarity": 0.929141976013416}, {"source": 41, "isCrit": false, "target": 4, "similarity": 0.925834193149633}, {"source": 41, "isCrit": true, "target": 37, "similarity": 0.905817730294414}, {"source": 95, "isCrit": true, "target": 43, "similarity": 0.958747903680113}, {"source": 95, "isCrit": true, "target": 51, "similarity": 0.953734817830221}, {"source": 95, "isCrit": true, "target": 81, "similarity": 0.938926412836593}, {"source": 95, "isCrit": false, "target": 57, "similarity": 0.934160592586467}, {"source": 95, "isCrit": false, "target": 25, "similarity": 0.927802358188704}, {"source": 52, "isCrit": true, "target": 60, "similarity": 0.956608550882103}, {"source": 52, "isCrit": false, "target": 41, "similarity": 0.930846528678169}, {"source": 52, "isCrit": true, "target": 74, "similarity": 0.923950999538258}, {"source": 52, "isCrit": false, "target": 4, "similarity": 0.916955816154173}, {"source": 52, "isCrit": false, "target": 73, "similarity": 0.91619262706355}, {"source": 52, "isCrit": true, "target": 15, "similarity": 0.860745097327327}, {"source": 23, "isCrit": true, "target": 0, "similarity": 0.949798060018192}, {"source": 23, "isCrit": false, "target": 51, "similarity": 0.93051480067642}, {"source": 23, "isCrit": false, "target": 43, "similarity": 0.921509302914248}, {"source": 23, "isCrit": false, "target": 57, "similarity": 0.91358878931405}, {"source": 23, "isCrit": false, "target": 35, "similarity": 0.909894109863785}, {"source": 23, "isCrit": true, "target": 89, "similarity": 0.908903627357841}, {"source": 5, "isCrit": true, "target": 43, "similarity": 0.909872480288758}, {"source": 5, "isCrit": false, "target": 57, "similarity": 0.88741885312994}, {"source": 5, "isCrit": false, "target": 95, "similarity": 0.881065688960506}, {"source": 5, "isCrit": false, "target": 51, "similarity": 0.873967328831604}, {"source": 5, "isCrit": false, "target": 23, "similarity": 0.864403327722022}, {"source": 86, "isCrit": true, "target": 11, "similarity": 0.849452903127786}, {"source": 86, "isCrit": false, "target": 75, "similarity": 0.840485734963878}, {"source": 86, "isCrit": false, "target": 53, "similarity": 0.84029775407271}, {"source": 86, "isCrit": false, "target": 29, "similarity": 0.836230174525197}, {"source": 86, "isCrit": false, "target": 18, "similarity": 0.833493403237103}, {"source": 9, "isCrit": true, "target": 51, "similarity": 0.922027901667062}, {"source": 9, "isCrit": false, "target": 57, "similarity": 0.915456350377065}, {"source": 9, "isCrit": false, "target": 32, "similarity": 0.91525631087372}, {"source": 9, "isCrit": false, "target": 43, "similarity": 0.903682864009213}, {"source": 9, "isCrit": false, "target": 35, "similarity": 0.896421523000684}, {"source": 51, "isCrit": true, "target": 0, "similarity": 0.956829126110312}, {"source": 51, "isCrit": true, "target": 95, "similarity": 0.953734817830221}, {"source": 51, "isCrit": false, "target": 43, "similarity": 0.952097128472532}, {"source": 51, "isCrit": false, "target": 57, "similarity": 0.94366944686971}, {"source": 51, "isCrit": false, "target": 35, "similarity": 0.943330194603982}, {"source": 51, "isCrit": true, "target": 73, "similarity": 0.938054817580393}, {"source": 51, "isCrit": true, "target": 9, "similarity": 0.922027901667062}, {"source": 51, "isCrit": true, "target": 38, "similarity": 0.919543051007654}, {"source": 51, "isCrit": true, "target": 59, "similarity": 0.918969829007277}, {"source": 51, "isCrit": true, "target": 8, "similarity": 0.91302485521905}, {"source": 51, "isCrit": true, "target": 45, "similarity": 0.88289905441436}, {"source": 51, "isCrit": true, "target": 61, "similarity": 0.858632542199069}, {"source": 63, "isCrit": true, "target": 29, "similarity": 0.954469786031149}, {"source": 63, "isCrit": false, "target": 11, "similarity": 0.953497955541591}, {"source": 63, "isCrit": false, "target": 10, "similarity": 0.948301944104815}, {"source": 63, "isCrit": false, "target": 53, "similarity": 0.948157078317604}, {"source": 63, "isCrit": false, "target": 24, "similarity": 0.930429446272417}, {"source": 18, "isCrit": true, "target": 11, "similarity": 0.951169900535766}, {"source": 18, "isCrit": false, "target": 12, "similarity": 0.947935662867754}, {"source": 18, "isCrit": false, "target": 53, "similarity": 0.946657964512729}, {"source": 18, "isCrit": false, "target": 21, "similarity": 0.930121267789193}, {"source": 18, "isCrit": false, "target": 29, "similarity": 0.9279091068898}, {"source": 76, "isCrit": true, "target": 54, "similarity": 0.960301573009194}, {"source": 76, "isCrit": true, "target": 78, "similarity": 0.948460554489613}, {"source": 76, "isCrit": false, "target": 57, "similarity": 0.946128320564189}, {"source": 76, "isCrit": false, "target": 46, "similarity": 0.946046443187501}, {"source": 76, "isCrit": true, "target": 33, "similarity": 0.944876197538999}, {"source": 85, "isCrit": true, "target": 31, "similarity": 0.957460094561875}, {"source": 85, "isCrit": false, "target": 58, "similarity": 0.806710096255949}, {"source": 85, "isCrit": false, "target": 78, "similarity": 0.742629089846416}, {"source": 85, "isCrit": false, "target": 2, "similarity": 0.72696422860562}, {"source": 85, "isCrit": false, "target": 47, "similarity": 0.724726108638638}, {"source": 66, "isCrit": true, "target": 11, "similarity": 0.842396514893741}, {"source": 66, "isCrit": false, "target": 21, "similarity": 0.829964959700214}, {"source": 66, "isCrit": false, "target": 24, "similarity": 0.82885693793964}, {"source": 66, "isCrit": false, "target": 18, "similarity": 0.825496021878068}, {"source": 66, "isCrit": false, "target": 80, "similarity": 0.825062811512071}, {"source": 68, "isCrit": true, "target": 54, "similarity": 0.827662241591875}, {"source": 68, "isCrit": false, "target": 33, "similarity": 0.826338909813501}, {"source": 68, "isCrit": false, "target": 76, "similarity": 0.822819922476152}, {"source": 68, "isCrit": false, "target": 2, "similarity": 0.81979302454607}, {"source": 68, "isCrit": false, "target": 78, "similarity": 0.819183362281784}, {"source": 38, "isCrit": true, "target": 72, "similarity": 0.933178472252642}, {"source": 38, "isCrit": false, "target": 17, "similarity": 0.929372701391017}, {"source": 38, "isCrit": false, "target": 41, "similarity": 0.929141976013416}, {"source": 38, "isCrit": true, "target": 51, "similarity": 0.919543051007654}, {"source": 38, "isCrit": false, "target": 35, "similarity": 0.917606441377055}, {"source": 38, "isCrit": true, "target": 16, "similarity": 0.901389366722965}, {"source": 38, "isCrit": true, "target": 92, "similarity": 0.788916246428544}, {"source": 77, "isCrit": true, "target": 53, "similarity": 0.876155302282353}, {"source": 77, "isCrit": false, "target": 10, "similarity": 0.873567119417032}, {"source": 77, "isCrit": false, "target": 29, "similarity": 0.870037203509341}, {"source": 77, "isCrit": false, "target": 11, "similarity": 0.865597996388663}, {"source": 77, "isCrit": false, "target": 90, "similarity": 0.850725659406126}, {"source": 35, "isCrit": true, "target": 57, "similarity": 0.963423709385343}, {"source": 35, "isCrit": true, "target": 78, "similarity": 0.957752907798319}, {"source": 35, "isCrit": true, "target": 14, "similarity": 0.953908510109041}, {"source": 35, "isCrit": false, "target": 43, "similarity": 0.950214083797075}, {"source": 35, "isCrit": true, "target": 48, "similarity": 0.949613668532322}, {"source": 35, "isCrit": true, "target": 44, "similarity": 0.941306150184896}, {"source": 35, "isCrit": true, "target": 94, "similarity": 0.781014846833701}, {"source": 65, "isCrit": true, "target": 17, "similarity": 0.896741897164488}, {"source": 65, "isCrit": false, "target": 72, "similarity": 0.892105925578206}, {"source": 65, "isCrit": false, "target": 16, "similarity": 0.889445831845728}, {"source": 65, "isCrit": false, "target": 38, "similarity": 0.875148183670882}, {"source": 65, "isCrit": false, "target": 84, "similarity": 0.853181372961071}, {"source": 2, "isCrit": true, "target": 78, "similarity": 0.956042662166534}, {"source": 2, "isCrit": false, "target": 35, "similarity": 0.945607407863885}, {"source": 2, "isCrit": false, "target": 57, "similarity": 0.937989695685432}, {"source": 2, "isCrit": false, "target": 14, "similarity": 0.933602222770604}, {"source": 2, "isCrit": false, "target": 76, "similarity": 0.932668739615409}, {"source": 21, "isCrit": true, "target": 11, "similarity": 0.954832998849478}, {"source": 21, "isCrit": false, "target": 53, "similarity": 0.935819118560684}, {"source": 21, "isCrit": false, "target": 29, "similarity": 0.934103965509417}, {"source": 21, "isCrit": false, "target": 12, "similarity": 0.933438373020112}, {"source": 21, "isCrit": false, "target": 7, "similarity": 0.932025265136496}, {"source": 67, "isCrit": true, "target": 7, "similarity": 0.916837780586109}, {"source": 67, "isCrit": false, "target": 11, "similarity": 0.897985994130988}, {"source": 67, "isCrit": false, "target": 29, "similarity": 0.883017826582767}, {"source": 67, "isCrit": false, "target": 36, "similarity": 0.872207123467613}, {"source": 67, "isCrit": false, "target": 53, "similarity": 0.871065960471941}, {"source": 12, "isCrit": true, "target": 11, "similarity": 0.960498271259815}, {"source": 12, "isCrit": false, "target": 53, "similarity": 0.95418010814397}, {"source": 12, "isCrit": false, "target": 18, "similarity": 0.947935662867754}, {"source": 12, "isCrit": false, "target": 7, "similarity": 0.943514920415059}, {"source": 12, "isCrit": false, "target": 21, "similarity": 0.933438373020112}, {"source": 12, "isCrit": true, "target": 19, "similarity": 0.926765354686791}, {"source": 15, "isCrit": true, "target": 52, "similarity": 0.860745097327327}, {"source": 15, "isCrit": false, "target": 81, "similarity": 0.860001251108117}, {"source": 15, "isCrit": false, "target": 41, "similarity": 0.851746557128547}, {"source": 15, "isCrit": false, "target": 51, "similarity": 0.85085587723765}, {"source": 15, "isCrit": false, "target": 20, "similarity": 0.844985000613696}, {"source": 36, "isCrit": true, "target": 60, "similarity": 0.948249189526292}, {"source": 36, "isCrit": true, "target": 6, "similarity": 0.92331111496572}, {"source": 36, "isCrit": false, "target": 4, "similarity": 0.909645732447515}, {"source": 36, "isCrit": false, "target": 52, "similarity": 0.901953285290452}, {"source": 36, "isCrit": false, "target": 7, "similarity": 0.892587680183706}, {"source": 20, "isCrit": true, "target": 55, "similarity": 0.912575236492953}, {"source": 20, "isCrit": false, "target": 81, "similarity": 0.907046413601185}, {"source": 20, "isCrit": false, "target": 18, "similarity": 0.892333207979931}, {"source": 20, "isCrit": false, "target": 53, "similarity": 0.891884811012612}, {"source": 20, "isCrit": false, "target": 27, "similarity": 0.89019299959941}, {"source": 4, "isCrit": true, "target": 60, "similarity": 0.951178217167601}, {"source": 4, "isCrit": false, "target": 41, "similarity": 0.925834193149633}, {"source": 4, "isCrit": false, "target": 52, "similarity": 0.916955816154173}, {"source": 4, "isCrit": false, "target": 36, "similarity": 0.909645732447515}, {"source": 4, "isCrit": false, "target": 10, "similarity": 0.904385340444279}, {"source": 7, "isCrit": true, "target": 11, "similarity": 0.965361673838801}, {"source": 7, "isCrit": false, "target": 12, "similarity": 0.943514920415059}, {"source": 7, "isCrit": false, "target": 53, "similarity": 0.93851669527825}, {"source": 7, "isCrit": false, "target": 21, "similarity": 0.932025265136496}, {"source": 7, "isCrit": false, "target": 29, "similarity": 0.924893402398314}, {"source": 7, "isCrit": true, "target": 67, "similarity": 0.916837780586109}, {"source": 30, "isCrit": true, "target": 43, "similarity": 0.878022649251538}, {"source": 30, "isCrit": false, "target": 51, "similarity": 0.877352449979069}, {"source": 30, "isCrit": false, "target": 25, "similarity": 0.86968932020275}, {"source": 30, "isCrit": false, "target": 8, "similarity": 0.866628737169124}, {"source": 30, "isCrit": false, "target": 95, "similarity": 0.86587797250882}, {"source": 42, "isCrit": true, "target": 11, "similarity": 0.9264289453337}, {"source": 42, "isCrit": false, "target": 80, "similarity": 0.920434014143191}, {"source": 42, "isCrit": false, "target": 21, "similarity": 0.909809640973244}, {"source": 42, "isCrit": false, "target": 24, "similarity": 0.909118863290393}, {"source": 42, "isCrit": false, "target": 29, "similarity": 0.907339160899681}, {"source": 74, "isCrit": true, "target": 52, "similarity": 0.923950999538258}, {"source": 74, "isCrit": false, "target": 60, "similarity": 0.922835303059977}, {"source": 74, "isCrit": false, "target": 41, "similarity": 0.91459921028876}, {"source": 74, "isCrit": false, "target": 51, "similarity": 0.898584553513396}, {"source": 74, "isCrit": false, "target": 53, "similarity": 0.896644522196465}, {"source": 28, "isCrit": true, "target": 57, "similarity": 0.919330633647839}, {"source": 28, "isCrit": false, "target": 43, "similarity": 0.913258717406152}, {"source": 28, "isCrit": false, "target": 35, "similarity": 0.912935613066354}, {"source": 28, "isCrit": false, "target": 51, "similarity": 0.905985710540174}, {"source": 28, "isCrit": false, "target": 78, "similarity": 0.89276107481251}, {"source": 78, "isCrit": true, "target": 35, "similarity": 0.957752907798319}, {"source": 78, "isCrit": true, "target": 2, "similarity": 0.956042662166534}, {"source": 78, "isCrit": false, "target": 57, "similarity": 0.950366084425963}, {"source": 78, "isCrit": true, "target": 76, "similarity": 0.948460554489613}, {"source": 78, "isCrit": false, "target": 43, "similarity": 0.939371787559782}, {"source": 78, "isCrit": true, "target": 47, "similarity": 0.890355491734164}, {"source": 78, "isCrit": true, "target": 50, "similarity": 0.885166015911932}, {"source": 78, "isCrit": true, "target": 49, "similarity": 0.831877175577253}, {"source": 47, "isCrit": true, "target": 78, "similarity": 0.890355491734164}, {"source": 47, "isCrit": false, "target": 35, "similarity": 0.887430110380477}, {"source": 47, "isCrit": false, "target": 57, "similarity": 0.882557014772379}, {"source": 47, "isCrit": false, "target": 33, "similarity": 0.877476220237308}, {"source": 47, "isCrit": false, "target": 2, "similarity": 0.874176054101394}, {"source": 90, "isCrit": true, "target": 53, "similarity": 0.936573778748317}, {"source": 90, "isCrit": false, "target": 10, "similarity": 0.933199149146494}, {"source": 90, "isCrit": false, "target": 29, "similarity": 0.933010892515918}, {"source": 90, "isCrit": false, "target": 11, "similarity": 0.923980422112507}, {"source": 90, "isCrit": false, "target": 63, "similarity": 0.916000752726915}, {"source": 57, "isCrit": true, "target": 35, "similarity": 0.963423709385343}, {"source": 57, "isCrit": true, "target": 43, "similarity": 0.963267708028916}, {"source": 57, "isCrit": false, "target": 78, "similarity": 0.950366084425963}, {"source": 57, "isCrit": true, "target": 46, "similarity": 0.946973741623033}, {"source": 57, "isCrit": false, "target": 76, "similarity": 0.946128320564189}, {"source": 57, "isCrit": true, "target": 28, "similarity": 0.919330633647839}, {"source": 0, "isCrit": true, "target": 51, "similarity": 0.956829126110312}, {"source": 0, "isCrit": true, "target": 23, "similarity": 0.949798060018192}, {"source": 0, "isCrit": false, "target": 43, "similarity": 0.925879909450414}, {"source": 0, "isCrit": false, "target": 95, "similarity": 0.923810110727261}, {"source": 0, "isCrit": false, "target": 35, "similarity": 0.923189843252145}, {"source": 59, "isCrit": true, "target": 51, "similarity": 0.918969829007277}, {"source": 59, "isCrit": false, "target": 73, "similarity": 0.918065141482255}, {"source": 59, "isCrit": false, "target": 81, "similarity": 0.901213313462165}, {"source": 59, "isCrit": false, "target": 52, "similarity": 0.897231379119029}, {"source": 59, "isCrit": false, "target": 74, "similarity": 0.883272248415628}, {"source": 48, "isCrit": true, "target": 35, "similarity": 0.949613668532322}, {"source": 48, "isCrit": false, "target": 14, "similarity": 0.931361550258155}, {"source": 48, "isCrit": false, "target": 57, "similarity": 0.929632894784643}, {"source": 48, "isCrit": false, "target": 51, "similarity": 0.927193841707251}, {"source": 48, "isCrit": false, "target": 43, "similarity": 0.920311644895965}, {"source": 1, "isCrit": true, "target": 10, "similarity": 0.879405231993347}, {"source": 1, "isCrit": false, "target": 53, "similarity": 0.859663137482903}, {"source": 1, "isCrit": false, "target": 29, "similarity": 0.852991395192871}, {"source": 1, "isCrit": false, "target": 71, "similarity": 0.846089607087615}, {"source": 1, "isCrit": false, "target": 90, "similarity": 0.831283169441974}, {"source": 93, "isCrit": true, "target": 60, "similarity": 0.900331413356144}, {"source": 93, "isCrit": false, "target": 52, "similarity": 0.898681427431034}, {"source": 93, "isCrit": false, "target": 53, "similarity": 0.888314224722182}, {"source": 93, "isCrit": false, "target": 10, "similarity": 0.879879275075446}, {"source": 93, "isCrit": false, "target": 74, "similarity": 0.879491803637221}, {"source": 39, "isCrit": true, "target": 80, "similarity": 0.912787430723249}, {"source": 39, "isCrit": false, "target": 11, "similarity": 0.906982097968027}, {"source": 39, "isCrit": false, "target": 42, "similarity": 0.894411566521383}, {"source": 39, "isCrit": false, "target": 63, "similarity": 0.894281765687921}, {"source": 39, "isCrit": false, "target": 75, "similarity": 0.888737867935781}, {"source": 39, "isCrit": true, "target": 40, "similarity": 0.786140751830102}, {"source": 79, "isCrit": true, "target": 11, "similarity": 0.857654461643192}, {"source": 79, "isCrit": false, "target": 29, "similarity": 0.851404789040416}, {"source": 79, "isCrit": false, "target": 63, "similarity": 0.848561060613117}, {"source": 79, "isCrit": false, "target": 53, "similarity": 0.848531855973692}, {"source": 79, "isCrit": false, "target": 18, "similarity": 0.842955202002768}, {"source": 55, "isCrit": true, "target": 24, "similarity": 0.928268496851117}, {"source": 55, "isCrit": false, "target": 18, "similarity": 0.915241164173936}, {"source": 55, "isCrit": false, "target": 63, "similarity": 0.913946157376886}, {"source": 55, "isCrit": true, "target": 20, "similarity": 0.912575236492953}, {"source": 55, "isCrit": false, "target": 12, "similarity": 0.909966831033032}, {"source": 56, "isCrit": true, "target": 80, "similarity": 0.866396051059021}, {"source": 56, "isCrit": false, "target": 11, "similarity": 0.848936114429579}, {"source": 56, "isCrit": false, "target": 42, "similarity": 0.845843082773765}, {"source": 56, "isCrit": false, "target": 21, "similarity": 0.84473644762224}, {"source": 56, "isCrit": false, "target": 24, "similarity": 0.83556325343807}, {"source": 17, "isCrit": true, "target": 72, "similarity": 0.936872665088151}, {"source": 17, "isCrit": true, "target": 41, "similarity": 0.930906441694013}, {"source": 17, "isCrit": false, "target": 38, "similarity": 0.929372701391017}, {"source": 17, "isCrit": true, "target": 65, "similarity": 0.896741897164488}, {"source": 17, "isCrit": false, "target": 60, "similarity": 0.89293557467968}, {"source": 24, "isCrit": true, "target": 11, "similarity": 0.937536044792101}, {"source": 24, "isCrit": false, "target": 63, "similarity": 0.930429446272417}, {"source": 24, "isCrit": false, "target": 53, "similarity": 0.928698426743591}, {"source": 24, "isCrit": true, "target": 55, "similarity": 0.928268496851117}, {"source": 24, "isCrit": false, "target": 18, "similarity": 0.92684550663254}, {"source": 13, "isCrit": true, "target": 75, "similarity": 0.827905315786243}, {"source": 13, "isCrit": false, "target": 11, "similarity": 0.815042826506352}, {"source": 13, "isCrit": false, "target": 29, "similarity": 0.81464202813756}, {"source": 13, "isCrit": false, "target": 53, "similarity": 0.805517444976521}, {"source": 13, "isCrit": false, "target": 63, "similarity": 0.805102670174476}, {"source": 92, "isCrit": true, "target": 38, "similarity": 0.788916246428544}, {"source": 92, "isCrit": false, "target": 51, "similarity": 0.780769712727123}, {"source": 92, "isCrit": false, "target": 41, "similarity": 0.767650640128387}, {"source": 92, "isCrit": false, "target": 17, "similarity": 0.766850781289507}, {"source": 92, "isCrit": false, "target": 90, "similarity": 0.763878648763609}, {"source": 84, "isCrit": true, "target": 72, "similarity": 0.916139895910011}, {"source": 84, "isCrit": false, "target": 38, "similarity": 0.905561798822387}, {"source": 84, "isCrit": false, "target": 16, "similarity": 0.883427212198677}, {"source": 84, "isCrit": false, "target": 17, "similarity": 0.880438501427843}, {"source": 84, "isCrit": false, "target": 35, "similarity": 0.874797131909415}, {"source": 83, "isCrit": true, "target": 60, "similarity": 0.821433245958374}, {"source": 83, "isCrit": false, "target": 41, "similarity": 0.798363814416533}, {"source": 83, "isCrit": false, "target": 52, "similarity": 0.792783168932693}, {"source": 83, "isCrit": false, "target": 26, "similarity": 0.786926401008858}, {"source": 83, "isCrit": false, "target": 4, "similarity": 0.7851656235466}, {"source": 71, "isCrit": true, "target": 53, "similarity": 0.947113001955749}, {"source": 71, "isCrit": false, "target": 10, "similarity": 0.936746949532046}, {"source": 71, "isCrit": false, "target": 11, "similarity": 0.919791362642184}, {"source": 71, "isCrit": false, "target": 29, "similarity": 0.911208605192623}, {"source": 71, "isCrit": false, "target": 63, "similarity": 0.907334068972828}, {"source": 60, "isCrit": true, "target": 52, "similarity": 0.956608550882103}, {"source": 60, "isCrit": true, "target": 4, "similarity": 0.951178217167601}, {"source": 60, "isCrit": true, "target": 41, "similarity": 0.949279418203958}, {"source": 60, "isCrit": true, "target": 36, "similarity": 0.948249189526292}, {"source": 60, "isCrit": true, "target": 11, "similarity": 0.926214797115394}, {"source": 60, "isCrit": true, "target": 82, "similarity": 0.925944680662694}, {"source": 60, "isCrit": true, "target": 69, "similarity": 0.922360576852026}, {"source": 60, "isCrit": true, "target": 26, "similarity": 0.917768509304121}, {"source": 60, "isCrit": true, "target": 93, "similarity": 0.900331413356144}, {"source": 60, "isCrit": true, "target": 22, "similarity": 0.894224332570103}, {"source": 60, "isCrit": true, "target": 64, "similarity": 0.875613767715995}, {"source": 60, "isCrit": true, "target": 83, "similarity": 0.821433245958374}, {"source": 34, "isCrit": true, "target": 54, "similarity": 0.829684350908428}, {"source": 34, "isCrit": false, "target": 33, "similarity": 0.829041445346326}, {"source": 34, "isCrit": false, "target": 14, "similarity": 0.82375376295405}, {"source": 34, "isCrit": false, "target": 78, "similarity": 0.823639720702665}, {"source": 34, "isCrit": false, "target": 2, "similarity": 0.817111528292819}, {"source": 73, "isCrit": true, "target": 51, "similarity": 0.938054817580393}, {"source": 73, "isCrit": false, "target": 54, "similarity": 0.929342825645374}, {"source": 73, "isCrit": false, "target": 59, "similarity": 0.918065141482255}, {"source": 73, "isCrit": false, "target": 52, "similarity": 0.91619262706355}, {"source": 73, "isCrit": false, "target": 33, "similarity": 0.915859712493977}, {"source": 61, "isCrit": true, "target": 51, "similarity": 0.858632542199069}, {"source": 61, "isCrit": false, "target": 16, "similarity": 0.851625224623599}, {"source": 61, "isCrit": false, "target": 89, "similarity": 0.845340587843642}, {"source": 61, "isCrit": false, "target": 38, "similarity": 0.844562853994452}, {"source": 61, "isCrit": false, "target": 17, "similarity": 0.832014404328974}, {"source": 45, "isCrit": true, "target": 51, "similarity": 0.88289905441436}, {"source": 45, "isCrit": false, "target": 9, "similarity": 0.863038638039356}, {"source": 45, "isCrit": false, "target": 52, "similarity": 0.85390504517491}, {"source": 45, "isCrit": false, "target": 8, "similarity": 0.850305390827968}, {"source": 45, "isCrit": false, "target": 73, "similarity": 0.848632195761137}, {"source": 44, "isCrit": true, "target": 35, "similarity": 0.941306150184896}, {"source": 44, "isCrit": false, "target": 78, "similarity": 0.933634354724295}, {"source": 44, "isCrit": false, "target": 14, "similarity": 0.931162929277093}, {"source": 44, "isCrit": false, "target": 76, "similarity": 0.930895773066449}, {"source": 44, "isCrit": false, "target": 33, "similarity": 0.924444655526617}, {"source": 29, "isCrit": true, "target": 53, "similarity": 0.969317614843408}, {"source": 29, "isCrit": false, "target": 11, "similarity": 0.965583731837888}, {"source": 29, "isCrit": false, "target": 10, "similarity": 0.960727694552045}, {"source": 29, "isCrit": true, "target": 63, "similarity": 0.954469786031149}, {"source": 29, "isCrit": false, "target": 87, "similarity": 0.938132030126731}, {"source": 29, "isCrit": true, "target": 88, "similarity": 0.908709937852244}, {"source": 6, "isCrit": true, "target": 36, "similarity": 0.92331111496572}, {"source": 6, "isCrit": false, "target": 60, "similarity": 0.896604771479381}, {"source": 6, "isCrit": false, "target": 72, "similarity": 0.888958435130392}, {"source": 6, "isCrit": false, "target": 35, "similarity": 0.878696077416625}, {"source": 6, "isCrit": false, "target": 4, "similarity": 0.87868209483857}, {"source": 3, "isCrit": true, "target": 11, "similarity": 0.904366687118201}, {"source": 3, "isCrit": false, "target": 24, "similarity": 0.899041427216799}, {"source": 3, "isCrit": false, "target": 18, "similarity": 0.896106197419024}, {"source": 3, "isCrit": false, "target": 63, "similarity": 0.894451290313517}, {"source": 3, "isCrit": false, "target": 12, "similarity": 0.892802776637719}, {"source": 62, "isCrit": true, "target": 11, "similarity": 0.869647170309687}, {"source": 62, "isCrit": false, "target": 12, "similarity": 0.866763251725427}, {"source": 62, "isCrit": false, "target": 53, "similarity": 0.85171217313554}, {"source": 62, "isCrit": false, "target": 21, "similarity": 0.849188206103847}, {"source": 62, "isCrit": false, "target": 63, "similarity": 0.848660950584579}, {"source": 19, "isCrit": true, "target": 12, "similarity": 0.926765354686791}, {"source": 19, "isCrit": false, "target": 11, "similarity": 0.925916764734351}, {"source": 19, "isCrit": false, "target": 18, "similarity": 0.908544920952159}, {"source": 19, "isCrit": false, "target": 53, "similarity": 0.907541127540985}, {"source": 19, "isCrit": false, "target": 21, "similarity": 0.901959511860627}, {"source": 10, "isCrit": true, "target": 53, "similarity": 0.977345517115847}, {"source": 10, "isCrit": false, "target": 29, "similarity": 0.960727694552045}, {"source": 10, "isCrit": false, "target": 11, "similarity": 0.956904076617522}, {"source": 10, "isCrit": false, "target": 63, "similarity": 0.948301944104815}, {"source": 10, "isCrit": false, "target": 71, "similarity": 0.936746949532046}, {"source": 10, "isCrit": true, "target": 1, "similarity": 0.879405231993347}, {"source": 40, "isCrit": true, "target": 39, "similarity": 0.786140751830102}, {"source": 40, "isCrit": false, "target": 80, "similarity": 0.778544525272229}, {"source": 40, "isCrit": false, "target": 75, "similarity": 0.772679426059141}, {"source": 40, "isCrit": false, "target": 11, "similarity": 0.772467216758784}, {"source": 40, "isCrit": false, "target": 42, "similarity": 0.758029893169122}, {"source": 33, "isCrit": true, "target": 76, "similarity": 0.944876197538999}, {"source": 33, "isCrit": false, "target": 54, "similarity": 0.943639794702702}, {"source": 33, "isCrit": false, "target": 35, "similarity": 0.936250435605909}, {"source": 33, "isCrit": false, "target": 78, "similarity": 0.934764462791094}, {"source": 33, "isCrit": false, "target": 14, "similarity": 0.932996854960294}, {"source": 25, "isCrit": true, "target": 81, "similarity": 0.931492053925161}, {"source": 25, "isCrit": false, "target": 95, "similarity": 0.927802358188704}, {"source": 25, "isCrit": false, "target": 51, "similarity": 0.92617028822625}, {"source": 25, "isCrit": false, "target": 73, "similarity": 0.908510157374396}, {"source": 25, "isCrit": false, "target": 27, "similarity": 0.905647883784437}, {"source": 14, "isCrit": true, "target": 35, "similarity": 0.953908510109041}, {"source": 14, "isCrit": false, "target": 78, "similarity": 0.934547759726128}, {"source": 14, "isCrit": false, "target": 2, "similarity": 0.933602222770604}, {"source": 14, "isCrit": false, "target": 33, "similarity": 0.932996854960294}, {"source": 14, "isCrit": false, "target": 57, "similarity": 0.932695802717289}, {"source": 27, "isCrit": true, "target": 81, "similarity": 0.910911578583094}, {"source": 27, "isCrit": false, "target": 25, "similarity": 0.905647883784437}, {"source": 27, "isCrit": false, "target": 20, "similarity": 0.89019299959941}, {"source": 27, "isCrit": false, "target": 52, "similarity": 0.88745909510351}, {"source": 27, "isCrit": false, "target": 55, "similarity": 0.882019534938429}, {"source": 80, "isCrit": true, "target": 11, "similarity": 0.939168619993736}, {"source": 80, "isCrit": false, "target": 29, "similarity": 0.921947910130428}, {"source": 80, "isCrit": false, "target": 21, "similarity": 0.920814977437279}, {"source": 80, "isCrit": false, "target": 42, "similarity": 0.920434014143191}, {"source": 80, "isCrit": false, "target": 63, "similarity": 0.916756617474093}, {"source": 80, "isCrit": true, "target": 39, "similarity": 0.912787430723249}, {"source": 80, "isCrit": true, "target": 56, "similarity": 0.866396051059021}, {"source": 80, "isCrit": true, "target": 58, "similarity": 0.801487046904586}, {"source": 72, "isCrit": true, "target": 17, "similarity": 0.936872665088151}, {"source": 72, "isCrit": true, "target": 38, "similarity": 0.933178472252642}, {"source": 72, "isCrit": true, "target": 84, "similarity": 0.916139895910011}, {"source": 72, "isCrit": false, "target": 41, "similarity": 0.911581154783922}, {"source": 72, "isCrit": false, "target": 35, "similarity": 0.893512061694449}, {"source": 69, "isCrit": true, "target": 60, "similarity": 0.922360576852026}, {"source": 69, "isCrit": false, "target": 41, "similarity": 0.907807445629329}, {"source": 69, "isCrit": false, "target": 4, "similarity": 0.902761349009095}, {"source": 69, "isCrit": false, "target": 52, "similarity": 0.902391428092234}, {"source": 69, "isCrit": false, "target": 74, "similarity": 0.886315513240306}, {"source": 64, "isCrit": true, "target": 60, "similarity": 0.875613767715995}, {"source": 64, "isCrit": false, "target": 26, "similarity": 0.859323535885617}, {"source": 64, "isCrit": false, "target": 4, "similarity": 0.856374105875136}, {"source": 64, "isCrit": false, "target": 41, "similarity": 0.853048518162278}, {"source": 64, "isCrit": false, "target": 11, "similarity": 0.839123448142017}, {"source": 89, "isCrit": true, "target": 23, "similarity": 0.908903627357841}, {"source": 89, "isCrit": false, "target": 0, "similarity": 0.90795925521767}, {"source": 89, "isCrit": false, "target": 51, "similarity": 0.904948951546529}, {"source": 89, "isCrit": false, "target": 16, "similarity": 0.878532517088659}, {"source": 89, "isCrit": false, "target": 38, "similarity": 0.875048610727654}, {"source": 22, "isCrit": true, "target": 60, "similarity": 0.894224332570103}, {"source": 22, "isCrit": false, "target": 52, "similarity": 0.878622168707391}, {"source": 22, "isCrit": false, "target": 41, "similarity": 0.868612815139659}, {"source": 22, "isCrit": false, "target": 26, "similarity": 0.868553913484015}, {"source": 22, "isCrit": false, "target": 4, "similarity": 0.864903925094212}, {"source": 26, "isCrit": true, "target": 60, "similarity": 0.917768509304121}, {"source": 26, "isCrit": false, "target": 52, "similarity": 0.898866234876654}, {"source": 26, "isCrit": false, "target": 41, "similarity": 0.891652612251986}, {"source": 26, "isCrit": false, "target": 4, "similarity": 0.888881847787998}, {"source": 26, "isCrit": false, "target": 33, "similarity": 0.88785212655941}, {"source": 49, "isCrit": true, "target": 78, "similarity": 0.831877175577253}, {"source": 49, "isCrit": false, "target": 2, "similarity": 0.822851057455847}, {"source": 49, "isCrit": false, "target": 35, "similarity": 0.80105153810888}, {"source": 49, "isCrit": false, "target": 57, "similarity": 0.797091438647569}, {"source": 49, "isCrit": false, "target": 76, "similarity": 0.79409078388081}, {"source": 43, "isCrit": true, "target": 57, "similarity": 0.963267708028916}, {"source": 43, "isCrit": true, "target": 95, "similarity": 0.958747903680113}, {"source": 43, "isCrit": false, "target": 51, "similarity": 0.952097128472532}, {"source": 43, "isCrit": false, "target": 35, "similarity": 0.950214083797075}, {"source": 43, "isCrit": true, "target": 32, "similarity": 0.940123179487731}, {"source": 43, "isCrit": true, "target": 5, "similarity": 0.909872480288758}, {"source": 43, "isCrit": true, "target": 30, "similarity": 0.878022649251538}, {"source": 94, "isCrit": true, "target": 35, "similarity": 0.781014846833701}, {"source": 94, "isCrit": false, "target": 51, "similarity": 0.779580239824516}, {"source": 94, "isCrit": false, "target": 14, "similarity": 0.767241615451665}, {"source": 94, "isCrit": false, "target": 44, "similarity": 0.764998907838286}, {"source": 94, "isCrit": false, "target": 76, "similarity": 0.76308902063408}, {"source": 81, "isCrit": true, "target": 95, "similarity": 0.938926412836593}, {"source": 81, "isCrit": true, "target": 25, "similarity": 0.931492053925161}, {"source": 81, "isCrit": false, "target": 51, "similarity": 0.926035718181523}, {"source": 81, "isCrit": false, "target": 73, "similarity": 0.91220975484636}, {"source": 81, "isCrit": true, "target": 27, "similarity": 0.910911578583094}, {"source": 53, "isCrit": true, "target": 10, "similarity": 0.977345517115847}, {"source": 53, "isCrit": true, "target": 11, "similarity": 0.972195066008033}, {"source": 53, "isCrit": true, "target": 29, "similarity": 0.969317614843408}, {"source": 53, "isCrit": false, "target": 12, "similarity": 0.95418010814397}, {"source": 53, "isCrit": false, "target": 63, "similarity": 0.948157078317604}, {"source": 53, "isCrit": true, "target": 71, "similarity": 0.947113001955749}, {"source": 53, "isCrit": true, "target": 87, "similarity": 0.938237421018231}, {"source": 53, "isCrit": true, "target": 90, "similarity": 0.936573778748317}, {"source": 53, "isCrit": true, "target": 70, "similarity": 0.905450918369276}, {"source": 53, "isCrit": true, "target": 77, "similarity": 0.876155302282353}, {"source": 46, "isCrit": true, "target": 57, "similarity": 0.946973741623033}, {"source": 46, "isCrit": false, "target": 76, "similarity": 0.946046443187501}, {"source": 46, "isCrit": false, "target": 35, "similarity": 0.939938519230244}, {"source": 46, "isCrit": false, "target": 78, "similarity": 0.934767806471784}, {"source": 46, "isCrit": false, "target": 54, "similarity": 0.924512269914571}, {"source": 16, "isCrit": true, "target": 38, "similarity": 0.901389366722965}, {"source": 16, "isCrit": false, "target": 65, "similarity": 0.889445831845728}, {"source": 16, "isCrit": false, "target": 0, "similarity": 0.885981237532851}, {"source": 16, "isCrit": false, "target": 51, "similarity": 0.885172353416842}, {"source": 16, "isCrit": false, "target": 84, "similarity": 0.883427212198677}, {"source": 75, "isCrit": true, "target": 11, "similarity": 0.94881054004812}, {"source": 75, "isCrit": false, "target": 29, "similarity": 0.936291885098813}, {"source": 75, "isCrit": false, "target": 53, "similarity": 0.930410817788686}, {"source": 75, "isCrit": false, "target": 10, "similarity": 0.923669333389669}, {"source": 75, "isCrit": false, "target": 21, "similarity": 0.921969632303078}, {"source": 75, "isCrit": true, "target": 13, "similarity": 0.827905315786243}, {"source": 88, "isCrit": true, "target": 29, "similarity": 0.908709937852244}, {"source": 88, "isCrit": false, "target": 53, "similarity": 0.908576581539269}, {"source": 88, "isCrit": false, "target": 10, "similarity": 0.900257224810588}, {"source": 88, "isCrit": false, "target": 11, "similarity": 0.898045682197512}, {"source": 88, "isCrit": false, "target": 63, "similarity": 0.892983327678806}, {"source": 37, "isCrit": true, "target": 41, "similarity": 0.905817730294414}, {"source": 37, "isCrit": false, "target": 52, "similarity": 0.895349257858617}, {"source": 37, "isCrit": false, "target": 60, "similarity": 0.895049353988082}, {"source": 37, "isCrit": false, "target": 38, "similarity": 0.883067648575593}, {"source": 37, "isCrit": false, "target": 74, "similarity": 0.877915605621596}, {"source": 32, "isCrit": true, "target": 43, "similarity": 0.940123179487731}, {"source": 32, "isCrit": false, "target": 57, "similarity": 0.937497801334137}, {"source": 32, "isCrit": false, "target": 9, "similarity": 0.91525631087372}, {"source": 32, "isCrit": false, "target": 51, "similarity": 0.909462595065253}, {"source": 32, "isCrit": false, "target": 95, "similarity": 0.905965406552319}, {"source": 82, "isCrit": true, "target": 60, "similarity": 0.925944680662694}, {"source": 82, "isCrit": false, "target": 41, "similarity": 0.912200737641721}, {"source": 82, "isCrit": false, "target": 52, "similarity": 0.905867088062053}, {"source": 82, "isCrit": false, "target": 4, "similarity": 0.899414197847398}, {"source": 82, "isCrit": false, "target": 69, "similarity": 0.883976834433473}, {"source": 11, "isCrit": true, "target": 53, "similarity": 0.972195066008033}, {"source": 11, "isCrit": false, "target": 29, "similarity": 0.965583731837888}, {"source": 11, "isCrit": true, "target": 7, "similarity": 0.965361673838801}, {"source": 11, "isCrit": true, "target": 12, "similarity": 0.960498271259815}, {"source": 11, "isCrit": false, "target": 10, "similarity": 0.956904076617522}, {"source": 11, "isCrit": true, "target": 21, "similarity": 0.954832998849478}, {"source": 11, "isCrit": true, "target": 18, "similarity": 0.951169900535766}, {"source": 11, "isCrit": true, "target": 75, "similarity": 0.94881054004812}, {"source": 11, "isCrit": true, "target": 80, "similarity": 0.939168619993736}, {"source": 11, "isCrit": true, "target": 24, "similarity": 0.937536044792101}, {"source": 11, "isCrit": true, "target": 42, "similarity": 0.9264289453337}, {"source": 11, "isCrit": true, "target": 60, "similarity": 0.926214797115394}, {"source": 11, "isCrit": true, "target": 91, "similarity": 0.919857018464628}, {"source": 11, "isCrit": true, "target": 3, "similarity": 0.904366687118201}, {"source": 11, "isCrit": true, "target": 62, "similarity": 0.869647170309687}, {"source": 11, "isCrit": true, "target": 79, "similarity": 0.857654461643192}, {"source": 11, "isCrit": true, "target": 86, "similarity": 0.849452903127786}, {"source": 11, "isCrit": true, "target": 66, "similarity": 0.842396514893741}, {"source": 8, "isCrit": true, "target": 51, "similarity": 0.91302485521905}, {"source": 8, "isCrit": false, "target": 95, "similarity": 0.905932234243861}, {"source": 8, "isCrit": false, "target": 81, "similarity": 0.900053188648867}, {"source": 8, "isCrit": false, "target": 25, "similarity": 0.899845604872999}, {"source": 8, "isCrit": false, "target": 73, "similarity": 0.897410685643317}, {"source": 70, "isCrit": true, "target": 53, "similarity": 0.905450918369276}, {"source": 70, "isCrit": false, "target": 12, "similarity": 0.893875389400643}, {"source": 70, "isCrit": false, "target": 24, "similarity": 0.890263900474367}, {"source": 70, "isCrit": false, "target": 88, "similarity": 0.889403286403144}, {"source": 70, "isCrit": false, "target": 11, "similarity": 0.887793772759207}, {"source": 91, "isCrit": true, "target": 11, "similarity": 0.919857018464628}, {"source": 91, "isCrit": false, "target": 53, "similarity": 0.908422772203206}, {"source": 91, "isCrit": false, "target": 12, "similarity": 0.906963864151593}, {"source": 91, "isCrit": false, "target": 18, "similarity": 0.90249385491461}, {"source": 91, "isCrit": false, "target": 19, "similarity": 0.900369817643855}, {"source": 58, "isCrit": true, "target": 31, "similarity": 0.899031493689773}, {"source": 58, "isCrit": false, "target": 85, "similarity": 0.806710096255949}, {"source": 58, "isCrit": true, "target": 80, "similarity": 0.801487046904586}, {"source": 58, "isCrit": false, "target": 42, "similarity": 0.7754794389638}, {"source": 58, "isCrit": false, "target": 39, "similarity": 0.757362984841139}]}