{"nodes": [{"count": 4033, "lender": "JP Morgan Chase", "purpose": "CASH-OUT REFINANCE", "d_count": 0, "i": 0, "dr": 0.0, "id": "010d8e6be0802699379a7b332072ecfd18bede01", "channel": "RETAIL"}, {"count": 2811, "lender": "Flagstar Bank", "purpose": "CASH-OUT REFINANCE", "d_count": 0, "i": 1, "dr": 0.0, "id": "03ac6357f2a67b30ceb6df24122902783dc268c1", "channel": "CORRESPONDENT"}, {"count": 751, "lender": "NYCB", "purpose": "OTHER REFINANCE", "d_count": 0, "i": 2, "dr": 0.0, "id": "0e3034660ca9d5211fdef5dbb7ab146e213141b8", "channel": "CORRESPONDENT"}, {"count": 1699, "lender": "Fed Home", "purpose": "CASH-OUT REFINANCE", "d_count": 1, "i": 3, "dr": 0.0006, "id": "0f84c5defcf715dc6aa71d3149e02e6ef7f375a1", "channel": "CORRESPONDENT"}, {"count": 270, "lender": "Franklin America", "purpose": "PURCHASE", "d_count": 0, "i": 4, "dr": 0.0, "id": "109b284e4f57141b97c396b413b329684a1bc03e", "channel": "RETAIL"}, {"count": 573, "lender": "Chicago Mortgage", "purpose": "CASH-OUT REFINANCE", "d_count": 0, "i": 5, "dr": 0.0, "id": "118ed0d387c3bf751eb22922a673a463cb15bc8f", "channel": "BROKER"}, {"count": 7462, "lender": "US Bank", "purpose": "PURCHASE", "d_count": 0, "i": 6, "dr": 0.0, "id": "11e9aced7c718ebe23b077825a865dc9a745c897", "channel": "CORRESPONDENT"}, {"count": 1612, "lender": "Bank of America", "purpose": "OTHER REFINANCE", "d_count": 0, "i": 7, "dr": 0.0, "id": "12c296d6c92b905a8c7690b4b8fef2d98cfa1f76", "channel": "RETAIL"}, {"count": 353, "lender": "Flagstar Bank", "purpose": "OTHER REFINANCE", "d_count": 0, "i": 8, "dr": 0.0, "id": "14379589b547d62e8ae2a8bed9aad1a6a0ecdd8a", "channel": "RETAIL"}, {"count": 3649, "lender": "US Bank", "purpose": "CASH-OUT REFINANCE", "d_count": 0, "i": 9, "dr": 0.0, "id": "17582b85aafee11ca80308b84c6401d004c0ca03", "channel": "CORRESPONDENT"}, {"count": 491, "lender": "Fifth Third Bank", "purpose": "PURCHASE", "d_count": 0, "i": 10, "dr": 0.0, "id": "179832544a27c68fc889a93595f97b6d24792635", "channel": "BROKER"}, {"count": 1365, "lender": "PHH Mortgage", "purpose": "OTHER REFINANCE", "d_count": 0, "i": 11, "dr": 0.0, "id": "179b45117144a52b3f47b730e81a832c9ac7074d", "channel": "CORRESPONDENT"}, {"count": 2047, "lender": "Ally Bank", "purpose": "PURCHASE", "d_count": 2, "i": 12, "dr": 0.001, "id": "1a7915d01597b51290e5b53a570344905a9bb96c", "channel": "CORRESPONDENT"}, {"count": 477, "lender": "Suntrust", "purpose": "CASH-OUT REFINANCE", "d_count": 0, "i": 13, "dr": 0.0, "id": "1e1792bc5ccaaa0976ffac7f9baa5a8cd385f5bd", "channel": "CORRESPONDENT"}, {"count": 320, "lender": "Ally Bank", "purpose": "PURCHASE", "d_count": 0, "i": 14, "dr": 0.0, "id": "1e7415cf2038f77005429ed9b415c05c6687e192", "channel": "RETAIL"}, {"count": 1694, "lender": "NYCB", "purpose": "PURCHASE", "d_count": 0, "i": 15, "dr": 0.0, "id": "24b99d9ff6e0f8fd7a750405f115b93a23e75938", "channel": "BROKER"}, {"count": 1205, "lender": "Guaranteed Rate", "purpose": "PURCHASE", "d_count": 0, "i": 16, "dr": 0.0, "id": "24e296194550e697cf6983e81a05e3b24803be96", "channel": "RETAIL"}, {"count": 659, "lender": "NYCB", "purpose": "CASH-OUT REFINANCE", "d_count": 0, "i": 17, "dr": 0.0, "id": "25a3fcdf0f2f359ef6fde970a9b9271dd5f69f51", "channel": "BROKER"}, {"count": 4459, "lender": "JP Morgan Chase", "purpose": "PURCHASE", "d_count": 0, "i": 18, "dr": 0.0, "id": "27746114f2563334b1134c5327e58ef4b3f30db7", "channel": "RETAIL"}, {"count": 366, "lender": "Ally Bank", "purpose": "PURCHASE", "d_count": 0, "i": 19, "dr": 0.0, "id": "28681842ad161d7e1a764085b7ca5f41312b58cd", "channel": "BROKER"}, {"count": 1718, "lender": "Fed Home", "purpose": "PURCHASE", "d_count": 1, "i": 20, "dr": 0.0006, "id": "2f7c6e9d19662997ba973fe549e527cf30084d10", "channel": "CORRESPONDENT"}, {"count": 819, "lender": "BB&T", "purpose": "CASH-OUT REFINANCE", "d_count": 0, "i": 21, "dr": 0.0, "id": "30f2e9b935234c3a73680f1e2c5f753ffdd54ec3", "channel": "RETAIL"}, {"count": 2094, "lender": "United Wholesale", "purpose": "OTHER REFINANCE", "d_count": 0, "i": 22, "dr": 0.0, "id": "31d576189553163582da04142fec92f3801bc58c", "channel": "BROKER"}, {"count": 1387, "lender": "Wells Fargo", "purpose": "OTHER REFINANCE", "d_count": 1, "i": 23, "dr": 0.0007, "id": "329a0efb1be91fa076c3fa5f9e3d1839b02c5231", "channel": "BROKER"}, {"count": 408, "lender": "Provident Funding", "purpose": "PURCHASE", "d_count": 0, "i": 24, "dr": 0.0, "id": "33c29d959e7ed0a4638937778cbea7fd9ed81a60", "channel": "CORRESPONDENT"}, {"count": 12608, "lender": "Wells Fargo", "purpose": "OTHER REFINANCE", "d_count": 0, "i": 25, "dr": 0.0, "id": "3693a118e3ad6a9a6d5c16d86a401d76024e1835", "channel": "RETAIL"}, {"count": 444, "lender": "Suntrust", "purpose": "PURCHASE", "d_count": 0, "i": 26, "dr": 0.0, "id": "399f32094c42a6c6d76ff29f76c543e059908a36", "channel": "BROKER"}, {"count": 834, "lender": "Quicken Loans", "purpose": "PURCHASE", "d_count": 0, "i": 27, "dr": 0.0, "id": "3a3503ac03826f7745a648b0a7f47ab003231a1f", "channel": "BROKER"}, {"count": 2514, "lender": "Chicago Mortgage", "purpose": "OTHER REFINANCE", "d_count": 0, "i": 28, "dr": 0.0, "id": "3a499438ad3d0dee67e2dafe8d7bf02d0e12578d", "channel": "BROKER"}, {"count": 8291, "lender": "Flagstar Bank", "purpose": "OTHER REFINANCE", "d_count": 1, "i": 29, "dr": 0.0001, "id": "3cb08dafcc3b3744df6d06eaeb01dc8840153354", "channel": "CORRESPONDENT"}, {"count": 882, "lender": "Citi", "purpose": "CASH-OUT REFINANCE", "d_count": 1, "i": 30, "dr": 0.0011, "id": "3e3fb9bd1df92c04abf362f8916d8fcca5ad7e56", "channel": "RETAIL"}, {"count": 5097, "lender": "BB&T", "purpose": "PURCHASE", "d_count": 2, "i": 31, "dr": 0.0004, "id": "4052e77ff64b1ac427d6ffb0b845bfc06a670f20", "channel": "CORRESPONDENT"}, {"count": 8615, "lender": "PennyMac", "purpose": "OTHER REFINANCE", "d_count": 2, "i": 32, "dr": 0.0002, "id": "40a897d38ae36adec9ae7441a2626ebb47f632d9", "channel": "CORRESPONDENT"}, {"count": 11955, "lender": "Wells Fargo", "purpose": "CASH-OUT REFINANCE", "d_count": 1, "i": 33, "dr": 0.0001, "id": "431496650d2aea9074f5e8fa473df4d367d9550a", "channel": "CORRESPONDENT"}, {"count": 259, "lender": "NYCB", "purpose": "CASH-OUT REFINANCE", "d_count": 0, "i": 34, "dr": 0.0, "id": "4573db5ddff141aa8de9e67cb0dbf7866f8ec6a8", "channel": "CORRESPONDENT"}, {"count": 255, "lender": "Ally Bank", "purpose": "CASH-OUT REFINANCE", "d_count": 0, "i": 35, "dr": 0.0, "id": "45d2781eea3bb6857e06775643e9c7b1c2e538c2", "channel": "BROKER"}, {"count": 5165, "lender": "Flagstar Bank", "purpose": "OTHER REFINANCE", "d_count": 1, "i": 36, "dr": 0.0002, "id": "4653e080c51a6df17384feec3c1ca41d8aced275", "channel": "BROKER"}, {"count": 44699, "lender": "Wells Fargo", "purpose": "OTHER REFINANCE", "d_count": 11, "i": 37, "dr": 0.0002, "id": "4701fa7c18b319783c2e13e58cc519c50217fb20", "channel": "CORRESPONDENT"}, {"count": 469, "lender": "Suntrust", "purpose": "CASH-OUT REFINANCE", "d_count": 0, "i": 38, "dr": 0.0, "id": "47022560c1cddb57bce2e24b946b50ab0dd21563", "channel": "RETAIL"}, {"count": 2428, "lender": "Homeward Mortgage", "purpose": "PURCHASE", "d_count": 0, "i": 39, "dr": 0.0, "id": "4bcdd2ef6f5d9e7ec0ac32325231df00a6a5f26d", "channel": "CORRESPONDENT"}, {"count": 1709, "lender": "Stearns Lending", "purpose": "PURCHASE", "d_count": 0, "i": 40, "dr": 0.0, "id": "4df63a933a722bcd95b52ba1564c3961fcaa64db", "channel": "BROKER"}, {"count": 709, "lender": "Fifth Third Bank", "purpose": "OTHER REFINANCE", "d_count": 0, "i": 41, "dr": 0.0, "id": "4f7be798b6075792b7f77bcc6c1c07e93debe4a3", "channel": "CORRESPONDENT"}, {"count": 762, "lender": "Citi", "purpose": "PURCHASE", "d_count": 1, "i": 42, "dr": 0.0013, "id": "500448e180ec43d5cc05ef80d513e8841c72bfd1", "channel": "CORRESPONDENT"}, {"count": 1161, "lender": "Suntrust", "purpose": "OTHER REFINANCE", "d_count": 0, "i": 43, "dr": 0.0, "id": "504842b54b954efd4a7958b52e4a827b26579696", "channel": "BROKER"}, {"count": 2744, "lender": "Amerisave", "purpose": "OTHER REFINANCE", "d_count": 0, "i": 44, "dr": 0.0, "id": "50e4167ae89b731f0b02657b2cd5cdbd8144f376", "channel": "RETAIL"}, {"count": 12978, "lender": "JP Morgan Chase", "purpose": "OTHER REFINANCE", "d_count": 1, "i": 45, "dr": 0.0001, "id": "5258aadf83d2ee8875fdca903f5dd447aa68d04c", "channel": "CORRESPONDENT"}, {"count": 1703, "lender": "PHH Mortgage", "purpose": "OTHER REFINANCE", "d_count": 0, "i": 46, "dr": 0.0, "id": "567057d9ecaf641240ec25a1b0f8a0d74c3b5798", "channel": "RETAIL"}, {"count": 356, "lender": "Chicago Mortgage", "purpose": "PURCHASE", "d_count": 0, "i": 47, "dr": 0.0, "id": "5832168a95e95835c4070cefe437c1de956dd279", "channel": "BROKER"}, {"count": 437, "lender": "Ally Bank", "purpose": "CASH-OUT REFINANCE", "d_count": 0, "i": 48, "dr": 0.0, "id": "5c97bc1254646acdafad8df973683fd07a63c282", "channel": "RETAIL"}, {"count": 4921, "lender": "BB&T", "purpose": "OTHER REFINANCE", "d_count": 0, "i": 49, "dr": 0.0, "id": "5f43a3ad1b322bb49bc45466d21e181281639fba", "channel": "CORRESPONDENT"}, {"count": 259, "lender": "Suntrust", "purpose": "CASH-OUT REFINANCE", "d_count": 0, "i": 50, "dr": 0.0, "id": "61b6d810d7d9727a8fc4f413e7073d3c6a67bd4a", "channel": "BROKER"}, {"count": 1513, "lender": "United Wholesale", "purpose": "PURCHASE", "d_count": 0, "i": 51, "dr": 0.0, "id": "64acb2d2a23c10c6c702873929ee3bca143bf5f4", "channel": "BROKER"}, {"count": 670, "lender": "Citi", "purpose": "CASH-OUT REFINANCE", "d_count": 0, "i": 52, "dr": 0.0, "id": "68a2d1d03a6cd162645475c0fd7be6c36aa41e37", "channel": "CORRESPONDENT"}, {"count": 2280, "lender": "Guaranteed Rate", "purpose": "OTHER REFINANCE", "d_count": 1, "i": 53, "dr": 0.0004, "id": "69d1ca3661440d3fd9096620c4915d886bfb77ba", "channel": "RETAIL"}, {"count": 3897, "lender": "Homeward Mortgage", "purpose": "OTHER REFINANCE", "d_count": 4, "i": 54, "dr": 0.001, "id": "6b951790be2e7d8f8fd59d6178685a4669d5b1d0", "channel": "CORRESPONDENT"}, {"count": 1012, "lender": "Amerisave", "purpose": "CASH-OUT REFINANCE", "d_count": 0, "i": 55, "dr": 0.0, "id": "6c1f10411a611710fdeaaf7b7bfaef8f26cbb058", "channel": "RETAIL"}, {"count": 6970, "lender": "Provident Funding", "purpose": "OTHER REFINANCE", "d_count": 0, "i": 56, "dr": 0.0, "id": "74b213438eddbb1ff00d8a4ade10e5354b0ea6d2", "channel": "BROKER"}, {"count": 277, "lender": "Stearns Lending", "purpose": "CASH-OUT REFINANCE", "d_count": 0, "i": 57, "dr": 0.0, "id": "75fc290076760e1ee82cd3762990908eaa53bdcc", "channel": "RETAIL"}, {"count": 991, "lender": "NYCB", "purpose": "PURCHASE", "d_count": 1, "i": 58, "dr": 0.001, "id": "77815dd5c0612f0c67925a79028689ac457ba8c9", "channel": "CORRESPONDENT"}, {"count": 1372, "lender": "Ally Bank", "purpose": "CASH-OUT REFINANCE", "d_count": 2, "i": 59, "dr": 0.0015, "id": "7f83f6e3bc1505a99976f6ab6b2b3d2d3fb9981a", "channel": "CORRESPONDENT"}, {"count": 2200, "lender": "Citi", "purpose": "OTHER REFINANCE", "d_count": 0, "i": 60, "dr": 0.0, "id": "7fd725f53df481934fa4a17d062afac1c4555736", "channel": "CORRESPONDENT"}, {"count": 3090, "lender": "NYCB", "purpose": "OTHER REFINANCE", "d_count": 0, "i": 61, "dr": 0.0, "id": "7fdf586709007c52d9b2bea606ad50187adda5f6", "channel": "BROKER"}, {"count": 4355, "lender": "Flagstar Bank", "purpose": "PURCHASE", "d_count": 3, "i": 62, "dr": 0.0007, "id": "82d9a4d7043778612801119fd45fd9ad141ef6aa", "channel": "CORRESPONDENT"}, {"count": 2002, "lender": "PHH Mortgage", "purpose": "PURCHASE", "d_count": 0, "i": 63, "dr": 0.0, "id": "83c0475e2add89b74a7f59340136cb734c98c3c1", "channel": "RETAIL"}, {"count": 724, "lender": "United Wholesale", "purpose": "CASH-OUT REFINANCE", "d_count": 0, "i": 64, "dr": 0.0, "id": "8423772e77180b73a726c46434f6e769e55d0634", "channel": "BROKER"}, {"count": 6848, "lender": "PennyMac", "purpose": "PURCHASE", "d_count": 1, "i": 65, "dr": 0.0001, "id": "85b6a8e4e47a4a17e6d7f6e4d4fb2235b267b16a", "channel": "CORRESPONDENT"}, {"count": 1858, "lender": "Suntrust", "purpose": "OTHER REFINANCE", "d_count": 0, "i": 66, "dr": 0.0, "id": "87a2ccbb70b0de0eab943fecd2f72bf4f7a69d77", "channel": "CORRESPONDENT"}, {"count": 1175, "lender": "Bank of America", "purpose": "CASH-OUT REFINANCE", "d_count": 0, "i": 67, "dr": 0.0, "id": "8a4d4e5b2ec8d5ca71adb6e6e41d419cd4ff1851", "channel": "RETAIL"}, {"count": 1325, "lender": "BB&T", "purpose": "PURCHASE", "d_count": 0, "i": 68, "dr": 0.0, "id": "8df313684eaa3b3ff4e9a75f646bd03590317386", "channel": "RETAIL"}, {"count": 2494, "lender": "Ally Bank", "purpose": "OTHER REFINANCE", "d_count": 1, "i": 69, "dr": 0.0004, "id": "907e43ccc613fe63d604a619012fa3610882bbbb", "channel": "CORRESPONDENT"}, {"count": 437, "lender": "Caliber Funding", "purpose": "CASH-OUT REFINANCE", "d_count": 0, "i": 70, "dr": 0.0, "id": "949e34b2a79e749c113450a12393c4741461db7e", "channel": "BROKER"}, {"count": 5294, "lender": "Wells Fargo", "purpose": "CASH-OUT REFINANCE", "d_count": 2, "i": 71, "dr": 0.0004, "id": "958b2e78d362ed427bced0bc49f27a5dfd1428a2", "channel": "RETAIL"}, {"count": 13242, "lender": "Wells Fargo", "purpose": "PURCHASE", "d_count": 6, "i": 72, "dr": 0.0005, "id": "98408b29d5a8921fa19695f30a6067d6bf9911ae", "channel": "RETAIL"}, {"count": 1141, "lender": "Stearns Lending", "purpose": "CASH-OUT REFINANCE", "d_count": 1, "i": 73, "dr": 0.0009, "id": "9a41c5c56a332164cf1c84dabbf86c90c5fc6bd1", "channel": "BROKER"}, {"count": 314, "lender": "Stearns Lending", "purpose": "PURCHASE", "d_count": 0, "i": 74, "dr": 0.0, "id": "9b615315c7eda14b0c9c6a3fd73f2a0b42069cf5", "channel": "CORRESPONDENT"}, {"count": 796, "lender": "Provident Funding", "purpose": "PURCHASE", "d_count": 0, "i": 75, "dr": 0.0, "id": "9b9a1c99ff745e9254adc003ac4b34b5d50b5499", "channel": "BROKER"}, {"count": 44546, "lender": "Wells Fargo", "purpose": "PURCHASE", "d_count": 17, "i": 76, "dr": 0.0004, "id": "9c3447fa710754a9c34d4500f6ef7146625c1da5", "channel": "CORRESPONDENT"}, {"count": 502, "lender": "Stearns Lending", "purpose": "PURCHASE", "d_count": 0, "i": 77, "dr": 0.0, "id": "9c4f7dbb5f14cd0caa1117c930a361bcf80dd743", "channel": "RETAIL"}, {"count": 2797, "lender": "PennyMac", "purpose": "CASH-OUT REFINANCE", "d_count": 4, "i": 78, "dr": 0.0014, "id": "9ff67b5a4f3b5d832affc16d28e3d1d3b89d2ab0", "channel": "CORRESPONDENT"}, {"count": 602, "lender": "Guaranteed Rate", "purpose": "CASH-OUT REFINANCE", "d_count": 1, "i": 79, "dr": 0.0017, "id": "a0112331f0693f97745f12945c2ae6fa5d9523e5", "channel": "RETAIL"}, {"count": 416, "lender": "Franklin America", "purpose": "CASH-OUT REFINANCE", "d_count": 0, "i": 80, "dr": 0.0, "id": "a1500af5b80b0c1f33d96f2e1d50ee9d45c6e31b", "channel": "BROKER"}, {"count": 1383, "lender": "Quicken Loans", "purpose": "PURCHASE", "d_count": 0, "i": 81, "dr": 0.0, "id": "a3cc3b6faea2389b49fa4e7d053a3a63ed93e3ff", "channel": "RETAIL"}, {"count": 1155, "lender": "Franklin America", "purpose": "OTHER REFINANCE", "d_count": 0, "i": 82, "dr": 0.0, "id": "a7d79066a70a083bd1e8b35eb09521e400455a22", "channel": "BROKER"}, {"count": 416, "lender": "Caliber Funding", "purpose": "OTHER REFINANCE", "d_count": 0, "i": 83, "dr": 0.0, "id": "a8184e392217541f014222cf0e60d6edc9f25749", "channel": "RETAIL"}, {"count": 8994, "lender": "Quicken Loans", "purpose": "OTHER REFINANCE", "d_count": 2, "i": 84, "dr": 0.0002, "id": "abd3e0e2f8f3402f61c5b0816c0592d0d9185543", "channel": "RETAIL"}, {"count": 9589, "lender": "JP Morgan Chase", "purpose": "PURCHASE", "d_count": 1, "i": 85, "dr": 0.0001, "id": "acf170f52801ae928c54adfb029526e9035b0703", "channel": "CORRESPONDENT"}, {"count": 483, "lender": "Fifth Third Bank", "purpose": "CASH-OUT REFINANCE", "d_count": 0, "i": 86, "dr": 0.0, "id": "ad99454f651195af8d56504738938999326ee4d6", "channel": "RETAIL"}, {"count": 2960, "lender": "Franklin America", "purpose": "PURCHASE", "d_count": 4, "i": 87, "dr": 0.0014, "id": "b0e5161ceaec7c99d6a1da0f6ad4c5c416242e1a", "channel": "CORRESPONDENT"}, {"count": 783, "lender": "PHH Mortgage", "purpose": "CASH-OUT REFINANCE", "d_count": 2, "i": 88, "dr": 0.0026, "id": "b2fc114419f9476ad90bdc21266d95168d895125", "channel": "RETAIL"}, {"count": 2539, "lender": "Provident Funding", "purpose": "OTHER REFINANCE", "d_count": 0, "i": 89, "dr": 0.0, "id": "b3ed4e6e5391aaaaf4259da1f8095a35ede8b01f", "channel": "RETAIL"}, {"count": 301, "lender": "Flagstar Bank", "purpose": "PURCHASE", "d_count": 0, "i": 90, "dr": 0.0, "id": "b7b61f7390f71a02f7559719c37dc61f85a6774e", "channel": "RETAIL"}, {"count": 1877, "lender": "Bank of America", "purpose": "PURCHASE", "d_count": 0, "i": 91, "dr": 0.0, "id": "b7d6943c994274e70251806e7ec2b6659ec76c85", "channel": "RETAIL"}, {"count": 1645, "lender": "Homeward Mortgage", "purpose": "CASH-OUT REFINANCE", "d_count": 2, "i": 92, "dr": 0.0012, "id": "b7db91fe2cf7d79127ad2d14092059315e43129c", "channel": "CORRESPONDENT"}, {"count": 313, "lender": "Wells Fargo", "purpose": "CASH-OUT REFINANCE", "d_count": 0, "i": 93, "dr": 0.0, "id": "bc3242500875648fb04e015cf5569dcce8253bd7", "channel": "BROKER"}, {"count": 545, "lender": "Stearns Lending", "purpose": "OTHER REFINANCE", "d_count": 0, "i": 94, "dr": 0.0, "id": "bee911273dd4d8523edab818d895c66310abba89", "channel": "RETAIL"}, {"count": 682, "lender": "US Bank", "purpose": "OTHER REFINANCE", "d_count": 0, "i": 95, "dr": 0.0, "id": "c185c16300182b0521172460547719d090ef5c7a", "channel": "BROKER"}, {"count": 525, "lender": "Fifth Third Bank", "purpose": "PURCHASE", "d_count": 0, "i": 96, "dr": 0.0, "id": "c19f4297d5e03e20fb8d3936ed40c60e3028f4b0", "channel": "CORRESPONDENT"}, {"count": 4291, "lender": "Quicken Loans", "purpose": "OTHER REFINANCE", "d_count": 0, "i": 97, "dr": 0.0, "id": "c3b84804341f4555c4ccb4591b75fb4d306af501", "channel": "BROKER"}, {"count": 633, "lender": "Caliber Funding", "purpose": "PURCHASE", "d_count": 0, "i": 98, "dr": 0.0, "id": "c571347de92ec6deca71b2bcd791e14d47e386c4", "channel": "BROKER"}, {"count": 1880, "lender": "US Bank", "purpose": "PURCHASE", "d_count": 2, "i": 99, "dr": 0.0011, "id": "c701601bcf5d112aadf7d81d6a62371b0b51bb38", "channel": "RETAIL"}, {"count": 1269, "lender": "Fifth Third Bank", "purpose": "PURCHASE", "d_count": 0, "i": 100, "dr": 0.0, "id": "c762c86633e2dc109448ea8cbada742a7bdd7809", "channel": "RETAIL"}, {"count": 6616, "lender": "JP Morgan Chase", "purpose": "OTHER REFINANCE", "d_count": 1, "i": 101, "dr": 0.0002, "id": "c7f4efe6c6c0be0502475f74fc0664cf52d65c66", "channel": "RETAIL"}, {"count": 1192, "lender": "US Bank", "purpose": "CASH-OUT REFINANCE", "d_count": 0, "i": 102, "dr": 0.0, "id": "c963dbe1dc73465871aca4856d777d7a1586def7", "channel": "RETAIL"}, {"count": 2719, "lender": "US Bank", "purpose": "OTHER REFINANCE", "d_count": 0, "i": 103, "dr": 0.0, "id": "ca3498d0ef580b8155b2e95169c4c7e2a7f3b7d0", "channel": "RETAIL"}, {"count": 308, "lender": "Stearns Lending", "purpose": "OTHER REFINANCE", "d_count": 0, "i": 104, "dr": 0.0, "id": "cb1e517e355a70cab3da015b20fc11d0a2ba1354", "channel": "CORRESPONDENT"}, {"count": 1612, "lender": "Provident Funding", "purpose": "CASH-OUT REFINANCE", "d_count": 0, "i": 105, "dr": 0.0, "id": "cee0cdd8d45f9c7041f37ad038fdc8629216daf8", "channel": "BROKER"}, {"count": 1356, "lender": "Citi", "purpose": "PURCHASE", "d_count": 0, "i": 106, "dr": 0.0, "id": "cf5ec354048c63b0f2e068810bf5d237c5cf3f81", "channel": "RETAIL"}, {"count": 1463, "lender": "Flagstar Bank", "purpose": "CASH-OUT REFINANCE", "d_count": 0, "i": 107, "dr": 0.0, "id": "cfbaa7a1afe0b0e47691b0f7015b27c13ffda818", "channel": "BROKER"}, {"count": 1341, "lender": "BB&T", "purpose": "OTHER REFINANCE", "d_count": 0, "i": 108, "dr": 0.0, "id": "d1de57dc8966d919377355b3670b2e22dfb63ff1", "channel": "RETAIL"}, {"count": 3407, "lender": "Franklin America", "purpose": "OTHER REFINANCE", "d_count": 1, "i": 109, "dr": 0.0003, "id": "d390656f1a5b2fe3f480595801539e415cb1fca9", "channel": "CORRESPONDENT"}, {"count": 1610, "lender": "Franklin America", "purpose": "CASH-OUT REFINANCE", "d_count": 1, "i": 110, "dr": 0.0006, "id": "d3b87f7416bbf36cf3fb2bb673737d940e03e566", "channel": "CORRESPONDENT"}, {"count": 2341, "lender": "Greenlight Financial", "purpose": "OTHER REFINANCE", "d_count": 0, "i": 111, "dr": 0.0, "id": "d44e0d8ad42e74e62897aa133365f15dc974e06e", "channel": "RETAIL"}, {"count": 553, "lender": "Ally Bank", "purpose": "OTHER REFINANCE", "d_count": 0, "i": 112, "dr": 0.0, "id": "d9f21a4ce85aa1dc8ead28ee4d9567d92fa75b68", "channel": "RETAIL"}, {"count": 3577, "lender": "Fed Home", "purpose": "OTHER REFINANCE", "d_count": 3, "i": 113, "dr": 0.0008, "id": "dbba4338a17297a66466077c94c2487ef62c62a6", "channel": "CORRESPONDENT"}, {"count": 1644, "lender": "Flagstar Bank", "purpose": "PURCHASE", "d_count": 2, "i": 114, "dr": 0.0012, "id": "dbbf60ae0a729c7ad81e960bd5aa13812f166f69", "channel": "BROKER"}, {"count": 10187, "lender": "US Bank", "purpose": "OTHER REFINANCE", "d_count": 1, "i": 115, "dr": 0.0001, "id": "de04871cf0e87c8eb6406129fb73fed822585e44", "channel": "CORRESPONDENT"}, {"count": 510, "lender": "Caliber Funding", "purpose": "PURCHASE", "d_count": 0, "i": 116, "dr": 0.0, "id": "e0b669002ed1c0d48ecbe7a43d5708e8a132f708", "channel": "RETAIL"}, {"count": 300, "lender": "Fifth Third Bank", "purpose": "CASH-OUT REFINANCE", "d_count": 0, "i": 117, "dr": 0.0, "id": "e37347cab897853394ff935be0d435496ad2f9f2", "channel": "CORRESPONDENT"}, {"count": 2137, "lender": "BB&T", "purpose": "CASH-OUT REFINANCE", "d_count": 0, "i": 118, "dr": 0.0, "id": "e3a460fc19d779b7f1167239ecd108178e8965b6", "channel": "CORRESPONDENT"}, {"count": 1194, "lender": "PHH Mortgage", "purpose": "PURCHASE", "d_count": 0, "i": 119, "dr": 0.0, "id": "e4750bef587eef1a7aec16f80c8b90c72d4836a3", "channel": "CORRESPONDENT"}, {"count": 1682, "lender": "Citi", "purpose": "OTHER REFINANCE", "d_count": 1, "i": 120, "dr": 0.0006, "id": "e532507f86a23da0130dd835489cd2e1a44b1184", "channel": "RETAIL"}, {"count": 3742, "lender": "JP Morgan Chase", "purpose": "CASH-OUT REFINANCE", "d_count": 1, "i": 121, "dr": 0.0003, "id": "e5c63e71dbca62dd44e08bd3b2a76966e69ff7de", "channel": "CORRESPONDENT"}, {"count": 438, "lender": "Wells Fargo", "purpose": "PURCHASE", "d_count": 0, "i": 122, "dr": 0.0, "id": "e6d1779218cef1617e96c20cf32644bd16af17a0", "channel": "BROKER"}, {"count": 434, "lender": "Provident Funding", "purpose": "CASH-OUT REFINANCE", "d_count": 0, "i": 123, "dr": 0.0, "id": "e7fb2532c32f0f49700f81061c24d519ca25adc7", "channel": "CORRESPONDENT"}, {"count": 936, "lender": "Franklin America", "purpose": "PURCHASE", "d_count": 1, "i": 124, "dr": 0.0011, "id": "eec4da84fa7b433ff54a1e409fcc7f1a0c325136", "channel": "BROKER"}, {"count": 1223, "lender": "Caliber Funding", "purpose": "OTHER REFINANCE", "d_count": 0, "i": 125, "dr": 0.0, "id": "eecdd10168a1b127c3d47546206199034e555208", "channel": "BROKER"}, {"count": 848, "lender": "PHH Mortgage", "purpose": "CASH-OUT REFINANCE", "d_count": 1, "i": 126, "dr": 0.0012, "id": "ef9c868d510a9bcad4a58ca42229113757f0b921", "channel": "CORRESPONDENT"}, {"count": 3038, "lender": "Stearns Lending", "purpose": "OTHER REFINANCE", "d_count": 1, "i": 127, "dr": 0.0003, "id": "f0604828e5430ff4a14f22f038a4001e8e9e80ce", "channel": "BROKER"}, {"count": 1491, "lender": "Suntrust", "purpose": "PURCHASE", "d_count": 0, "i": 128, "dr": 0.0, "id": "f36a59014e046b3d1cfe660533fff6e69256793f", "channel": "RETAIL"}, {"count": 720, "lender": "Amerisave", "purpose": "OTHER REFINANCE", "d_count": 0, "i": 129, "dr": 0.0, "id": "f4ac6f38f8f8d4ed70de94a40e98433e1db14b5e", "channel": "BROKER"}, {"count": 815, "lender": "Suntrust", "purpose": "PURCHASE", "d_count": 0, "i": 130, "dr": 0.0, "id": "f5cf893fea7dac5d2b73ba0ac82c51f25783211a", "channel": "CORRESPONDENT"}, {"count": 1116, "lender": "Quicken Loans", "purpose": "CASH-OUT REFINANCE", "d_count": 1, "i": 131, "dr": 0.0009, "id": "f7d3aaed0778e8b9677ba5e3d7444a34f6ab6b44", "channel": "BROKER"}, {"count": 737, "lender": "Ally Bank", "purpose": "OTHER REFINANCE", "d_count": 0, "i": 132, "dr": 0.0, "id": "f7e5ee836500f92bd1e3b646a3104d9466a7b85e", "channel": "BROKER"}, {"count": 1093, "lender": "Greenlight Financial", "purpose": "CASH-OUT REFINANCE", "d_count": 0, "i": 133, "dr": 0.0, "id": "f7f9d573c8e8082a1e37abe879805da06f1dd163", "channel": "RETAIL"}, {"count": 606, "lender": "Provident Funding", "purpose": "CASH-OUT REFINANCE", "d_count": 0, "i": 134, "dr": 0.0, "id": "f92beb7f100ce277c16c107f0a65ff6639b658b8", "channel": "RETAIL"}, {"count": 698, "lender": "Suntrust", "purpose": "OTHER REFINANCE", "d_count": 0, "i": 135, "dr": 0.0, "id": "fb47ada1b153971e627947e83e700e5dbf334cc8", "channel": "RETAIL"}, {"count": 3414, "lender": "Quicken Loans", "purpose": "CASH-OUT REFINANCE", "d_count": 6, "i": 136, "dr": 0.0018, "id": "fb4ecc52a7b170a95c922a8bbfb595427683940d", "channel": "RETAIL"}, {"count": 397, "lender": "Fifth Third Bank", "purpose": "OTHER REFINANCE", "d_count": 0, "i": 137, "dr": 0.0, "id": "fbcc34b3ba4678bfcb91b0bf4894bb66285b797c", "channel": "BROKER"}, {"count": 1385, "lender": "Provident Funding", "purpose": "OTHER REFINANCE", "d_count": 0, "i": 138, "dr": 0.0, "id": "fca0c0e4d86e77e76eeaa29894eea42fd6d172d0", "channel": "CORRESPONDENT"}, {"count": 1165, "lender": "Fifth Third Bank", "purpose": "OTHER REFINANCE", "d_count": 0, "i": 139, "dr": 0.0, "id": "fd33f892314037de8b2f11fe4a528e1e6c2aa905", "channel": "RETAIL"}], "meta": {"quarter": 4, "top_n": 5, "year": 2012}, "links": [{"source": 45, "isCrit": true, "target": 37, "similarity": 0.981976963085237}, {"source": 45, "isCrit": false, "target": 29, "similarity": 0.979398636259452}, {"source": 45, "isCrit": false, "target": 84, "similarity": 0.979102273111304}, {"source": 45, "isCrit": false, "target": 32, "similarity": 0.978761146765867}, {"source": 45, "isCrit": false, "target": 115, "similarity": 0.975108724246004}, {"source": 21, "isCrit": true, "target": 9, "similarity": 0.966995571083706}, {"source": 21, "isCrit": false, "target": 118, "similarity": 0.961746366263139}, {"source": 21, "isCrit": false, "target": 0, "similarity": 0.957145405459705}, {"source": 21, "isCrit": false, "target": 71, "similarity": 0.955222738897844}, {"source": 21, "isCrit": false, "target": 121, "similarity": 0.953898440298804}, {"source": 108, "isCrit": true, "target": 25, "similarity": 0.96839220868351}, {"source": 108, "isCrit": false, "target": 29, "similarity": 0.966970386537852}, {"source": 108, "isCrit": false, "target": 101, "similarity": 0.966821464543637}, {"source": 108, "isCrit": false, "target": 45, "similarity": 0.964432534382425}, {"source": 108, "isCrit": false, "target": 61, "similarity": 0.96401099771527}, {"source": 96, "isCrit": true, "target": 72, "similarity": 0.921954829539572}, {"source": 96, "isCrit": false, "target": 6, "similarity": 0.91803473724371}, {"source": 96, "isCrit": false, "target": 18, "similarity": 0.912716050963183}, {"source": 96, "isCrit": false, "target": 76, "similarity": 0.91150295119024}, {"source": 96, "isCrit": false, "target": 31, "similarity": 0.910191142341779}, {"source": 119, "isCrit": true, "target": 76, "similarity": 0.95796641793888}, {"source": 119, "isCrit": false, "target": 65, "similarity": 0.95365051078352}, {"source": 119, "isCrit": false, "target": 6, "similarity": 0.952819664988997}, {"source": 119, "isCrit": false, "target": 85, "similarity": 0.95278591252578}, {"source": 119, "isCrit": false, "target": 72, "similarity": 0.95111765787697}, {"source": 116, "isCrit": true, "target": 6, "similarity": 0.95044402380081}, {"source": 116, "isCrit": false, "target": 31, "similarity": 0.947542272684597}, {"source": 116, "isCrit": false, "target": 76, "similarity": 0.944272521893927}, {"source": 116, "isCrit": false, "target": 99, "similarity": 0.940371587736949}, {"source": 116, "isCrit": false, "target": 72, "similarity": 0.940368270471961}, {"source": 8, "isCrit": true, "target": 29, "similarity": 0.935976038639453}, {"source": 8, "isCrit": false, "target": 44, "similarity": 0.934501426014144}, {"source": 8, "isCrit": false, "target": 101, "similarity": 0.928031535688048}, {"source": 8, "isCrit": false, "target": 66, "similarity": 0.92745309437969}, {"source": 8, "isCrit": false, "target": 60, "similarity": 0.92685937719537}, {"source": 81, "isCrit": true, "target": 6, "similarity": 0.952593874319656}, {"source": 81, "isCrit": false, "target": 76, "similarity": 0.951581076040884}, {"source": 81, "isCrit": false, "target": 31, "similarity": 0.949491715526726}, {"source": 81, "isCrit": false, "target": 65, "similarity": 0.942915798592855}, {"source": 81, "isCrit": false, "target": 16, "similarity": 0.940920988693437}, {"source": 83, "isCrit": true, "target": 32, "similarity": 0.924327484497403}, {"source": 83, "isCrit": false, "target": 37, "similarity": 0.923539706972173}, {"source": 83, "isCrit": false, "target": 53, "similarity": 0.922958003168242}, {"source": 83, "isCrit": false, "target": 115, "similarity": 0.921580002421258}, {"source": 83, "isCrit": false, "target": 127, "similarity": 0.919839961466786}, {"source": 117, "isCrit": true, "target": 9, "similarity": 0.937466287042329}, {"source": 117, "isCrit": false, "target": 71, "similarity": 0.935219422993478}, {"source": 117, "isCrit": false, "target": 92, "similarity": 0.933548177030987}, {"source": 117, "isCrit": false, "target": 118, "similarity": 0.926519063982112}, {"source": 117, "isCrit": false, "target": 1, "similarity": 0.925189681912399}, {"source": 65, "isCrit": true, "target": 76, "similarity": 0.991266969781959}, {"source": 65, "isCrit": false, "target": 6, "similarity": 0.976290364645985}, {"source": 65, "isCrit": true, "target": 85, "similarity": 0.972842994747225}, {"source": 65, "isCrit": false, "target": 87, "similarity": 0.971888876442388}, {"source": 65, "isCrit": false, "target": 31, "similarity": 0.970238892488916}, {"source": 65, "isCrit": true, "target": 40, "similarity": 0.958082238938593}, {"source": 65, "isCrit": true, "target": 14, "similarity": 0.900684313336204}, {"source": 63, "isCrit": true, "target": 76, "similarity": 0.966204881173907}, {"source": 63, "isCrit": false, "target": 65, "similarity": 0.964842256717827}, {"source": 63, "isCrit": false, "target": 72, "similarity": 0.963102622620442}, {"source": 63, "isCrit": false, "target": 85, "similarity": 0.958707370269362}, {"source": 63, "isCrit": false, "target": 6, "similarity": 0.956735328303799}, {"source": 63, "isCrit": true, "target": 90, "similarity": 0.8972080388909}, {"source": 60, "isCrit": true, "target": 97, "similarity": 0.979413729124948}, {"source": 60, "isCrit": false, "target": 101, "similarity": 0.978059225648859}, {"source": 60, "isCrit": false, "target": 29, "similarity": 0.97575997914614}, {"source": 60, "isCrit": false, "target": 36, "similarity": 0.975132216016087}, {"source": 60, "isCrit": false, "target": 25, "similarity": 0.97359439929653}, {"source": 30, "isCrit": true, "target": 1, "similarity": 0.958957618395528}, {"source": 30, "isCrit": false, "target": 107, "similarity": 0.956924538608838}, {"source": 30, "isCrit": false, "target": 71, "similarity": 0.955343451489782}, {"source": 30, "isCrit": false, "target": 78, "similarity": 0.953508315397394}, {"source": 30, "isCrit": false, "target": 67, "similarity": 0.953455787688271}, {"source": 118, "isCrit": true, "target": 9, "similarity": 0.974638634288806}, {"source": 118, "isCrit": false, "target": 21, "similarity": 0.961746366263139}, {"source": 118, "isCrit": false, "target": 1, "similarity": 0.960103436646202}, {"source": 118, "isCrit": false, "target": 0, "similarity": 0.95791583818159}, {"source": 118, "isCrit": false, "target": 71, "similarity": 0.956953074001394}, {"source": 56, "isCrit": true, "target": 89, "similarity": 0.988465710483248}, {"source": 56, "isCrit": true, "target": 97, "similarity": 0.982442708308227}, {"source": 56, "isCrit": false, "target": 36, "similarity": 0.981486538977206}, {"source": 56, "isCrit": true, "target": 28, "similarity": 0.979536401031809}, {"source": 56, "isCrit": true, "target": 43, "similarity": 0.979501777386827}, {"source": 56, "isCrit": true, "target": 95, "similarity": 0.95552601092894}, {"source": 124, "isCrit": true, "target": 76, "similarity": 0.960610653325799}, {"source": 124, "isCrit": false, "target": 65, "similarity": 0.957129031166539}, {"source": 124, "isCrit": false, "target": 6, "similarity": 0.951410840371635}, {"source": 124, "isCrit": false, "target": 87, "similarity": 0.949919027304699}, {"source": 124, "isCrit": false, "target": 31, "similarity": 0.94701964668888}, {"source": 122, "isCrit": true, "target": 72, "similarity": 0.922992153354024}, {"source": 122, "isCrit": false, "target": 18, "similarity": 0.918972334901981}, {"source": 122, "isCrit": false, "target": 40, "similarity": 0.90999446583146}, {"source": 122, "isCrit": false, "target": 85, "similarity": 0.909936973432653}, {"source": 122, "isCrit": false, "target": 114, "similarity": 0.907667344291009}, {"source": 13, "isCrit": true, "target": 33, "similarity": 0.943596769667802}, {"source": 13, "isCrit": false, "target": 36, "similarity": 0.937932122411611}, {"source": 13, "isCrit": false, "target": 55, "similarity": 0.937525716483742}, {"source": 13, "isCrit": false, "target": 0, "similarity": 0.9355099775531}, {"source": 13, "isCrit": false, "target": 101, "similarity": 0.935232231602029}, {"source": 71, "isCrit": true, "target": 9, "similarity": 0.979201061894335}, {"source": 71, "isCrit": true, "target": 67, "similarity": 0.975257046608221}, {"source": 71, "isCrit": false, "target": 1, "similarity": 0.971502863748192}, {"source": 71, "isCrit": false, "target": 107, "similarity": 0.970065802768875}, {"source": 71, "isCrit": false, "target": 0, "similarity": 0.967368676397516}, {"source": 11, "isCrit": true, "target": 37, "similarity": 0.974828646533121}, {"source": 11, "isCrit": false, "target": 32, "similarity": 0.972810679310686}, {"source": 11, "isCrit": false, "target": 115, "similarity": 0.971678101066902}, {"source": 11, "isCrit": false, "target": 54, "similarity": 0.970948080967022}, {"source": 11, "isCrit": false, "target": 61, "similarity": 0.970526062851171}, {"source": 11, "isCrit": true, "target": 41, "similarity": 0.948458786654429}, {"source": 49, "isCrit": true, "target": 115, "similarity": 0.985192120487506}, {"source": 49, "isCrit": false, "target": 37, "similarity": 0.983734392757487}, {"source": 49, "isCrit": true, "target": 109, "similarity": 0.978869513929276}, {"source": 49, "isCrit": false, "target": 32, "similarity": 0.973622591403281}, {"source": 49, "isCrit": false, "target": 84, "similarity": 0.969853712461555}, {"source": 19, "isCrit": true, "target": 40, "similarity": 0.915380918141528}, {"source": 19, "isCrit": false, "target": 62, "similarity": 0.911094766934737}, {"source": 19, "isCrit": false, "target": 65, "similarity": 0.906071527521491}, {"source": 19, "isCrit": false, "target": 85, "similarity": 0.905999755990548}, {"source": 19, "isCrit": false, "target": 76, "similarity": 0.905781579747557}, {"source": 93, "isCrit": true, "target": 107, "similarity": 0.930941269875994}, {"source": 93, "isCrit": false, "target": 131, "similarity": 0.92790451294772}, {"source": 93, "isCrit": false, "target": 105, "similarity": 0.926714010102523}, {"source": 93, "isCrit": false, "target": 0, "similarity": 0.925329448644303}, {"source": 93, "isCrit": false, "target": 88, "similarity": 0.922873637195062}, {"source": 125, "isCrit": true, "target": 37, "similarity": 0.969501993486321}, {"source": 125, "isCrit": false, "target": 84, "similarity": 0.969296601987617}, {"source": 125, "isCrit": false, "target": 32, "similarity": 0.968821406570459}, {"source": 125, "isCrit": false, "target": 29, "similarity": 0.967552596083104}, {"source": 125, "isCrit": false, "target": 45, "similarity": 0.967409879916911}, {"source": 106, "isCrit": true, "target": 72, "similarity": 0.958896599747964}, {"source": 106, "isCrit": false, "target": 18, "similarity": 0.941247722782292}, {"source": 106, "isCrit": false, "target": 6, "similarity": 0.940910642528431}, {"source": 106, "isCrit": false, "target": 128, "similarity": 0.937355775877623}, {"source": 106, "isCrit": false, "target": 85, "similarity": 0.934706609115567}, {"source": 52, "isCrit": true, "target": 1, "similarity": 0.954783267578564}, {"source": 52, "isCrit": false, "target": 71, "similarity": 0.954751227523437}, {"source": 52, "isCrit": false, "target": 78, "similarity": 0.953644095085419}, {"source": 52, "isCrit": false, "target": 0, "similarity": 0.950442698469423}, {"source": 52, "isCrit": false, "target": 9, "similarity": 0.949920429494169}, {"source": 73, "isCrit": true, "target": 1, "similarity": 0.966335151850805}, {"source": 73, "isCrit": false, "target": 78, "similarity": 0.964141137171662}, {"source": 73, "isCrit": false, "target": 33, "similarity": 0.963738827987585}, {"source": 73, "isCrit": false, "target": 0, "similarity": 0.962566142513899}, {"source": 73, "isCrit": false, "target": 92, "similarity": 0.959133132226222}, {"source": 59, "isCrit": true, "target": 136, "similarity": 0.960598507585344}, {"source": 59, "isCrit": false, "target": 1, "similarity": 0.9480554661189}, {"source": 59, "isCrit": false, "target": 78, "similarity": 0.945802874522895}, {"source": 59, "isCrit": false, "target": 110, "similarity": 0.940182036385241}, {"source": 59, "isCrit": false, "target": 9, "similarity": 0.932077418354803}, {"source": 1, "isCrit": true, "target": 78, "similarity": 0.97765122862698}, {"source": 1, "isCrit": true, "target": 9, "similarity": 0.97552847716641}, {"source": 1, "isCrit": true, "target": 92, "similarity": 0.972251478243341}, {"source": 1, "isCrit": false, "target": 33, "similarity": 0.971504228453823}, {"source": 1, "isCrit": false, "target": 71, "similarity": 0.971502863748192}, {"source": 1, "isCrit": true, "target": 107, "similarity": 0.970513879748199}, {"source": 1, "isCrit": true, "target": 131, "similarity": 0.967096598063328}, {"source": 1, "isCrit": true, "target": 73, "similarity": 0.966335151850805}, {"source": 1, "isCrit": true, "target": 30, "similarity": 0.958957618395528}, {"source": 1, "isCrit": true, "target": 52, "similarity": 0.954783267578564}, {"source": 1, "isCrit": true, "target": 70, "similarity": 0.947026133420038}, {"source": 91, "isCrit": true, "target": 72, "similarity": 0.960077548173284}, {"source": 91, "isCrit": false, "target": 6, "similarity": 0.945099700757344}, {"source": 91, "isCrit": false, "target": 65, "similarity": 0.942470477908091}, {"source": 91, "isCrit": false, "target": 76, "similarity": 0.942147466939944}, {"source": 91, "isCrit": false, "target": 63, "similarity": 0.940421294561613}, {"source": 104, "isCrit": true, "target": 97, "similarity": 0.920775157717401}, {"source": 104, "isCrit": false, "target": 127, "similarity": 0.920397917880013}, {"source": 104, "isCrit": false, "target": 25, "similarity": 0.920069511818383}, {"source": 104, "isCrit": false, "target": 61, "similarity": 0.919203957056256}, {"source": 104, "isCrit": false, "target": 32, "similarity": 0.917632679965914}, {"source": 87, "isCrit": true, "target": 76, "similarity": 0.975008789439673}, {"source": 87, "isCrit": false, "target": 65, "similarity": 0.971888876442388}, {"source": 87, "isCrit": false, "target": 31, "similarity": 0.95814680271891}, {"source": 87, "isCrit": false, "target": 6, "similarity": 0.957253060055135}, {"source": 87, "isCrit": false, "target": 12, "similarity": 0.951012304833263}, {"source": 43, "isCrit": true, "target": 56, "similarity": 0.979501777386827}, {"source": 43, "isCrit": false, "target": 36, "similarity": 0.975001059305831}, {"source": 43, "isCrit": false, "target": 89, "similarity": 0.973614836095235}, {"source": 43, "isCrit": false, "target": 101, "similarity": 0.972497823031002}, {"source": 43, "isCrit": false, "target": 97, "similarity": 0.971307415615968}, {"source": 89, "isCrit": true, "target": 56, "similarity": 0.988465710483248}, {"source": 89, "isCrit": false, "target": 28, "similarity": 0.978532869928923}, {"source": 89, "isCrit": false, "target": 101, "similarity": 0.977310437273292}, {"source": 89, "isCrit": false, "target": 36, "similarity": 0.976972463490947}, {"source": 89, "isCrit": false, "target": 97, "similarity": 0.976798825499567}, {"source": 62, "isCrit": true, "target": 85, "similarity": 0.970570763674631}, {"source": 62, "isCrit": true, "target": 114, "similarity": 0.969815709663598}, {"source": 62, "isCrit": false, "target": 65, "similarity": 0.966936739279163}, {"source": 62, "isCrit": false, "target": 76, "similarity": 0.963726818103625}, {"source": 62, "isCrit": false, "target": 15, "similarity": 0.955433288298729}, {"source": 103, "isCrit": true, "target": 37, "similarity": 0.979342262903173}, {"source": 103, "isCrit": false, "target": 32, "similarity": 0.978454305473742}, {"source": 103, "isCrit": false, "target": 84, "similarity": 0.977336759489471}, {"source": 103, "isCrit": false, "target": 29, "similarity": 0.976572093755419}, {"source": 103, "isCrit": false, "target": 115, "similarity": 0.975027188015995}, {"source": 90, "isCrit": true, "target": 63, "similarity": 0.8972080388909}, {"source": 90, "isCrit": false, "target": 65, "similarity": 0.896337920471843}, {"source": 90, "isCrit": false, "target": 76, "similarity": 0.895624628726465}, {"source": 90, "isCrit": false, "target": 31, "similarity": 0.891556743947287}, {"source": 90, "isCrit": false, "target": 6, "similarity": 0.891524172106308}, {"source": 38, "isCrit": true, "target": 9, "similarity": 0.947517759604886}, {"source": 38, "isCrit": false, "target": 67, "similarity": 0.947495989076061}, {"source": 38, "isCrit": false, "target": 71, "similarity": 0.941446791376867}, {"source": 38, "isCrit": false, "target": 107, "similarity": 0.939630170612773}, {"source": 38, "isCrit": false, "target": 1, "similarity": 0.939565318870499}, {"source": 107, "isCrit": true, "target": 1, "similarity": 0.970513879748199}, {"source": 107, "isCrit": false, "target": 71, "similarity": 0.970065802768875}, {"source": 107, "isCrit": false, "target": 0, "similarity": 0.96778494727533}, {"source": 107, "isCrit": false, "target": 67, "similarity": 0.964829058538292}, {"source": 107, "isCrit": false, "target": 78, "similarity": 0.963114890190857}, {"source": 107, "isCrit": true, "target": 93, "similarity": 0.930941269875994}, {"source": 22, "isCrit": true, "target": 37, "similarity": 0.978317558369276}, {"source": 22, "isCrit": false, "target": 115, "similarity": 0.977822830953265}, {"source": 22, "isCrit": false, "target": 32, "similarity": 0.973666374834143}, {"source": 22, "isCrit": false, "target": 54, "similarity": 0.970693469318853}, {"source": 22, "isCrit": false, "target": 49, "similarity": 0.968879199737206}, {"source": 98, "isCrit": true, "target": 6, "similarity": 0.93842362611799}, {"source": 98, "isCrit": false, "target": 40, "similarity": 0.935521937895692}, {"source": 98, "isCrit": false, "target": 99, "similarity": 0.93415669758877}, {"source": 98, "isCrit": false, "target": 85, "similarity": 0.934145289650974}, {"source": 98, "isCrit": false, "target": 76, "similarity": 0.933664001946912}, {"source": 10, "isCrit": true, "target": 6, "similarity": 0.927092596551579}, {"source": 10, "isCrit": false, "target": 72, "similarity": 0.926000904770357}, {"source": 10, "isCrit": false, "target": 76, "similarity": 0.923705112186924}, {"source": 10, "isCrit": false, "target": 65, "similarity": 0.920580914169917}, {"source": 10, "isCrit": false, "target": 31, "similarity": 0.918066699641163}, {"source": 80, "isCrit": true, "target": 9, "similarity": 0.939537560472174}, {"source": 80, "isCrit": false, "target": 71, "similarity": 0.935743582976957}, {"source": 80, "isCrit": false, "target": 1, "similarity": 0.933685790717566}, {"source": 80, "isCrit": false, "target": 118, "similarity": 0.932208914722938}, {"source": 80, "isCrit": false, "target": 67, "similarity": 0.930026612306002}, {"source": 123, "isCrit": true, "target": 55, "similarity": 0.935886602143994}, {"source": 123, "isCrit": false, "target": 9, "similarity": 0.933296510916957}, {"source": 123, "isCrit": false, "target": 134, "similarity": 0.932946259129895}, {"source": 123, "isCrit": false, "target": 17, "similarity": 0.93241968947351}, {"source": 123, "isCrit": false, "target": 107, "similarity": 0.932095512531127}, {"source": 17, "isCrit": true, "target": 105, "similarity": 0.960174679343684}, {"source": 17, "isCrit": false, "target": 134, "similarity": 0.952707416520116}, {"source": 17, "isCrit": false, "target": 0, "similarity": 0.952461059330535}, {"source": 17, "isCrit": false, "target": 28, "similarity": 0.952033273620855}, {"source": 17, "isCrit": false, "target": 55, "similarity": 0.946823030821939}, {"source": 17, "isCrit": true, "target": 34, "similarity": 0.925615888828337}, {"source": 128, "isCrit": true, "target": 72, "similarity": 0.952830999631805}, {"source": 128, "isCrit": false, "target": 85, "similarity": 0.952544082599846}, {"source": 128, "isCrit": false, "target": 18, "similarity": 0.952271749890489}, {"source": 128, "isCrit": false, "target": 63, "similarity": 0.951481231315834}, {"source": 128, "isCrit": false, "target": 62, "similarity": 0.945967812659407}, {"source": 74, "isCrit": true, "target": 6, "similarity": 0.903353016025231}, {"source": 74, "isCrit": false, "target": 40, "similarity": 0.897251655338137}, {"source": 74, "isCrit": false, "target": 76, "similarity": 0.896651281459777}, {"source": 74, "isCrit": false, "target": 62, "similarity": 0.896156380752967}, {"source": 74, "isCrit": false, "target": 65, "similarity": 0.896031165476154}, {"source": 0, "isCrit": true, "target": 9, "similarity": 0.973931901054439}, {"source": 0, "isCrit": false, "target": 121, "similarity": 0.97334793190948}, {"source": 0, "isCrit": false, "target": 33, "similarity": 0.972029247163155}, {"source": 0, "isCrit": false, "target": 1, "similarity": 0.969370463699705}, {"source": 0, "isCrit": false, "target": 78, "similarity": 0.968228122356008}, {"source": 0, "isCrit": true, "target": 105, "similarity": 0.961782562388272}, {"source": 86, "isCrit": true, "target": 9, "similarity": 0.950489724839737}, {"source": 86, "isCrit": false, "target": 118, "similarity": 0.948210213359819}, {"source": 86, "isCrit": false, "target": 21, "similarity": 0.946577651956606}, {"source": 86, "isCrit": false, "target": 71, "similarity": 0.94060658850881}, {"source": 86, "isCrit": false, "target": 1, "similarity": 0.93912868115147}, {"source": 58, "isCrit": true, "target": 15, "similarity": 0.949126843360407}, {"source": 58, "isCrit": false, "target": 62, "similarity": 0.944212614432009}, {"source": 58, "isCrit": false, "target": 85, "similarity": 0.944197198075072}, {"source": 58, "isCrit": false, "target": 65, "similarity": 0.942928161493018}, {"source": 58, "isCrit": false, "target": 76, "similarity": 0.938987158121653}, {"source": 109, "isCrit": true, "target": 49, "similarity": 0.978869513929276}, {"source": 109, "isCrit": false, "target": 37, "similarity": 0.977044434256912}, {"source": 109, "isCrit": false, "target": 115, "similarity": 0.976108252191547}, {"source": 109, "isCrit": false, "target": 69, "similarity": 0.968228243694358}, {"source": 109, "isCrit": false, "target": 54, "similarity": 0.96588559784734}, {"source": 109, "isCrit": true, "target": 113, "similarity": 0.964938683469049}, {"source": 109, "isCrit": true, "target": 72, "similarity": 0.941711689006963}, {"source": 39, "isCrit": true, "target": 76, "similarity": 0.964632562724038}, {"source": 39, "isCrit": false, "target": 65, "similarity": 0.959531169611195}, {"source": 39, "isCrit": false, "target": 6, "similarity": 0.957225167400437}, {"source": 39, "isCrit": false, "target": 72, "similarity": 0.957177328045276}, {"source": 39, "isCrit": false, "target": 31, "similarity": 0.953085170836157}, {"source": 139, "isCrit": true, "target": 37, "similarity": 0.966105243827405}, {"source": 139, "isCrit": false, "target": 115, "similarity": 0.965971704607568}, {"source": 139, "isCrit": false, "target": 49, "similarity": 0.961272968544743}, {"source": 139, "isCrit": false, "target": 103, "similarity": 0.958637543784442}, {"source": 139, "isCrit": false, "target": 32, "similarity": 0.957711522102352}, {"source": 3, "isCrit": true, "target": 33, "similarity": 0.951709308069246}, {"source": 3, "isCrit": false, "target": 110, "similarity": 0.949220622383177}, {"source": 3, "isCrit": false, "target": 118, "similarity": 0.941876839262674}, {"source": 3, "isCrit": false, "target": 55, "similarity": 0.939085046384153}, {"source": 3, "isCrit": false, "target": 78, "similarity": 0.938879610059196}, {"source": 76, "isCrit": true, "target": 65, "similarity": 0.991266969781959}, {"source": 76, "isCrit": true, "target": 6, "similarity": 0.985758572290652}, {"source": 76, "isCrit": false, "target": 31, "similarity": 0.97811012944273}, {"source": 76, "isCrit": true, "target": 87, "similarity": 0.975008789439673}, {"source": 76, "isCrit": false, "target": 72, "similarity": 0.973564798399153}, {"source": 76, "isCrit": true, "target": 63, "similarity": 0.966204881173907}, {"source": 76, "isCrit": true, "target": 39, "similarity": 0.964632562724038}, {"source": 76, "isCrit": true, "target": 51, "similarity": 0.962875863443947}, {"source": 76, "isCrit": true, "target": 124, "similarity": 0.960610653325799}, {"source": 76, "isCrit": true, "target": 119, "similarity": 0.95796641793888}, {"source": 76, "isCrit": true, "target": 12, "similarity": 0.956849175454137}, {"source": 76, "isCrit": true, "target": 4, "similarity": 0.905743615338944}, {"source": 68, "isCrit": true, "target": 72, "similarity": 0.945740899264155}, {"source": 68, "isCrit": false, "target": 6, "similarity": 0.941638846077222}, {"source": 68, "isCrit": false, "target": 31, "similarity": 0.93973338766267}, {"source": 68, "isCrit": false, "target": 99, "similarity": 0.939396630399541}, {"source": 68, "isCrit": false, "target": 18, "similarity": 0.939259173112163}, {"source": 138, "isCrit": true, "target": 44, "similarity": 0.970076351239301}, {"source": 138, "isCrit": false, "target": 29, "similarity": 0.968357562765333}, {"source": 138, "isCrit": false, "target": 61, "similarity": 0.967299491369306}, {"source": 138, "isCrit": false, "target": 32, "similarity": 0.966762677829042}, {"source": 138, "isCrit": false, "target": 97, "similarity": 0.965911569926463}, {"source": 32, "isCrit": true, "target": 37, "similarity": 0.992654293917992}, {"source": 32, "isCrit": false, "target": 84, "similarity": 0.985918080908192}, {"source": 32, "isCrit": false, "target": 115, "similarity": 0.98588285437695}, {"source": 32, "isCrit": false, "target": 54, "similarity": 0.983861062479758}, {"source": 32, "isCrit": true, "target": 29, "similarity": 0.983555280609945}, {"source": 32, "isCrit": true, "target": 83, "similarity": 0.924327484497403}, {"source": 135, "isCrit": true, "target": 61, "similarity": 0.955380672134195}, {"source": 135, "isCrit": false, "target": 29, "similarity": 0.955310606369142}, {"source": 135, "isCrit": false, "target": 66, "similarity": 0.95301968981419}, {"source": 135, "isCrit": false, "target": 25, "similarity": 0.952692761516638}, {"source": 135, "isCrit": false, "target": 101, "similarity": 0.951784523968254}, {"source": 120, "isCrit": true, "target": 25, "similarity": 0.976660689429397}, {"source": 120, "isCrit": false, "target": 36, "similarity": 0.97542492451503}, {"source": 120, "isCrit": false, "target": 101, "similarity": 0.973481220754534}, {"source": 120, "isCrit": false, "target": 29, "similarity": 0.96996337804273}, {"source": 120, "isCrit": false, "target": 60, "similarity": 0.969775535929604}, {"source": 44, "isCrit": true, "target": 66, "similarity": 0.97781070590333}, {"source": 44, "isCrit": false, "target": 61, "similarity": 0.97475385932626}, {"source": 44, "isCrit": false, "target": 97, "similarity": 0.973793513246619}, {"source": 44, "isCrit": false, "target": 29, "similarity": 0.972991955785378}, {"source": 44, "isCrit": false, "target": 101, "similarity": 0.971952370250357}, {"source": 44, "isCrit": true, "target": 138, "similarity": 0.970076351239301}, {"source": 44, "isCrit": true, "target": 129, "similarity": 0.967578877863936}, {"source": 54, "isCrit": true, "target": 37, "similarity": 0.985818850439507}, {"source": 54, "isCrit": false, "target": 32, "similarity": 0.983861062479758}, {"source": 54, "isCrit": false, "target": 115, "similarity": 0.981876266590097}, {"source": 54, "isCrit": false, "target": 84, "similarity": 0.978930506915781}, {"source": 54, "isCrit": false, "target": 25, "similarity": 0.977541544406563}, {"source": 94, "isCrit": true, "target": 84, "similarity": 0.937830218431544}, {"source": 94, "isCrit": false, "target": 32, "similarity": 0.932721020730762}, {"source": 94, "isCrit": false, "target": 29, "similarity": 0.932454841941052}, {"source": 94, "isCrit": false, "target": 127, "similarity": 0.931895453977314}, {"source": 94, "isCrit": false, "target": 111, "similarity": 0.929882668366501}, {"source": 100, "isCrit": true, "target": 31, "similarity": 0.960008584877378}, {"source": 100, "isCrit": false, "target": 6, "similarity": 0.957813131684697}, {"source": 100, "isCrit": false, "target": 76, "similarity": 0.953813334847116}, {"source": 100, "isCrit": false, "target": 72, "similarity": 0.947131723510075}, {"source": 100, "isCrit": false, "target": 65, "similarity": 0.941153089754012}, {"source": 31, "isCrit": true, "target": 6, "similarity": 0.985441206284586}, {"source": 31, "isCrit": false, "target": 76, "similarity": 0.97811012944273}, {"source": 31, "isCrit": false, "target": 65, "similarity": 0.970238892488916}, {"source": 31, "isCrit": false, "target": 72, "similarity": 0.969292429912344}, {"source": 31, "isCrit": false, "target": 99, "similarity": 0.965330143638736}, {"source": 31, "isCrit": true, "target": 100, "similarity": 0.960008584877378}, {"source": 31, "isCrit": true, "target": 20, "similarity": 0.943291234428217}, {"source": 48, "isCrit": true, "target": 9, "similarity": 0.942936216503977}, {"source": 48, "isCrit": false, "target": 1, "similarity": 0.937876310102594}, {"source": 48, "isCrit": false, "target": 78, "similarity": 0.937199802464081}, {"source": 48, "isCrit": false, "target": 71, "similarity": 0.935592808228828}, {"source": 48, "isCrit": false, "target": 67, "similarity": 0.934165372780162}, {"source": 20, "isCrit": true, "target": 31, "similarity": 0.943291234428217}, {"source": 20, "isCrit": false, "target": 72, "similarity": 0.94321409239168}, {"source": 20, "isCrit": false, "target": 6, "similarity": 0.939977994278325}, {"source": 20, "isCrit": false, "target": 100, "similarity": 0.935100646971736}, {"source": 20, "isCrit": false, "target": 39, "similarity": 0.934758885700823}, {"source": 75, "isCrit": true, "target": 18, "similarity": 0.929549176565272}, {"source": 75, "isCrit": false, "target": 72, "similarity": 0.927070040456897}, {"source": 75, "isCrit": false, "target": 130, "similarity": 0.925456541440587}, {"source": 75, "isCrit": false, "target": 128, "similarity": 0.922393132736571}, {"source": 75, "isCrit": false, "target": 42, "similarity": 0.922305528035565}, {"source": 47, "isCrit": true, "target": 18, "similarity": 0.891132296536834}, {"source": 47, "isCrit": false, "target": 26, "similarity": 0.885431927809681}, {"source": 47, "isCrit": false, "target": 75, "similarity": 0.874543070504646}, {"source": 47, "isCrit": false, "target": 128, "similarity": 0.86999565478634}, {"source": 47, "isCrit": false, "target": 130, "similarity": 0.869902971071611}, {"source": 127, "isCrit": true, "target": 84, "similarity": 0.98392097435455}, {"source": 127, "isCrit": false, "target": 37, "similarity": 0.982041588501832}, {"source": 127, "isCrit": false, "target": 32, "similarity": 0.981425709442}, {"source": 127, "isCrit": false, "target": 115, "similarity": 0.976940857116884}, {"source": 127, "isCrit": false, "target": 29, "similarity": 0.975985641083091}, {"source": 57, "isCrit": true, "target": 33, "similarity": 0.906298862482613}, {"source": 57, "isCrit": false, "target": 73, "similarity": 0.904128660433118}, {"source": 57, "isCrit": false, "target": 1, "similarity": 0.903956935904696}, {"source": 57, "isCrit": false, "target": 0, "similarity": 0.900621457862246}, {"source": 57, "isCrit": false, "target": 107, "similarity": 0.89994762923872}, {"source": 102, "isCrit": true, "target": 9, "similarity": 0.965383954797223}, {"source": 102, "isCrit": false, "target": 0, "similarity": 0.964175525932903}, {"source": 102, "isCrit": false, "target": 121, "similarity": 0.959686414308679}, {"source": 102, "isCrit": false, "target": 33, "similarity": 0.958028280233524}, {"source": 102, "isCrit": false, "target": 79, "similarity": 0.95610808365048}, {"source": 66, "isCrit": true, "target": 44, "similarity": 0.97781070590333}, {"source": 66, "isCrit": true, "target": 61, "similarity": 0.975746962390426}, {"source": 66, "isCrit": false, "target": 101, "similarity": 0.970707289934849}, {"source": 66, "isCrit": false, "target": 29, "similarity": 0.969082366284237}, {"source": 66, "isCrit": false, "target": 97, "similarity": 0.967983411066033}, {"source": 137, "isCrit": true, "target": 61, "similarity": 0.930475364011393}, {"source": 137, "isCrit": false, "target": 101, "similarity": 0.927070254741663}, {"source": 137, "isCrit": false, "target": 54, "similarity": 0.924172511248349}, {"source": 137, "isCrit": false, "target": 32, "similarity": 0.924053042344082}, {"source": 137, "isCrit": false, "target": 108, "similarity": 0.923629838714595}, {"source": 42, "isCrit": true, "target": 72, "similarity": 0.945800614958682}, {"source": 42, "isCrit": false, "target": 85, "similarity": 0.945743150002737}, {"source": 42, "isCrit": false, "target": 18, "similarity": 0.94567522328025}, {"source": 42, "isCrit": false, "target": 128, "similarity": 0.94271067115849}, {"source": 42, "isCrit": false, "target": 62, "similarity": 0.940664564077444}, {"source": 7, "isCrit": true, "target": 36, "similarity": 0.973369231899439}, {"source": 7, "isCrit": false, "target": 25, "similarity": 0.971993319554103}, {"source": 7, "isCrit": false, "target": 97, "similarity": 0.969835502110141}, {"source": 7, "isCrit": false, "target": 101, "similarity": 0.969456616070469}, {"source": 7, "isCrit": false, "target": 56, "similarity": 0.965563813219134}, {"source": 114, "isCrit": true, "target": 62, "similarity": 0.969815709663598}, {"source": 114, "isCrit": false, "target": 85, "similarity": 0.955140029505189}, {"source": 114, "isCrit": false, "target": 18, "similarity": 0.94900699118651}, {"source": 114, "isCrit": false, "target": 40, "similarity": 0.945657710782536}, {"source": 114, "isCrit": false, "target": 65, "similarity": 0.942525277572209}, {"source": 105, "isCrit": true, "target": 134, "similarity": 0.969288593921551}, {"source": 105, "isCrit": true, "target": 0, "similarity": 0.961782562388272}, {"source": 105, "isCrit": true, "target": 17, "similarity": 0.960174679343684}, {"source": 105, "isCrit": false, "target": 107, "similarity": 0.958517972646103}, {"source": 105, "isCrit": false, "target": 102, "similarity": 0.953791905910033}, {"source": 105, "isCrit": true, "target": 5, "similarity": 0.953044754257555}, {"source": 26, "isCrit": true, "target": 18, "similarity": 0.93996130879842}, {"source": 26, "isCrit": false, "target": 85, "similarity": 0.922104154308292}, {"source": 26, "isCrit": false, "target": 114, "similarity": 0.916522441611668}, {"source": 26, "isCrit": false, "target": 75, "similarity": 0.915385937458585}, {"source": 26, "isCrit": false, "target": 128, "similarity": 0.91414286575419}, {"source": 18, "isCrit": true, "target": 72, "similarity": 0.960700512271495}, {"source": 18, "isCrit": false, "target": 85, "similarity": 0.959672567803352}, {"source": 18, "isCrit": false, "target": 128, "similarity": 0.952271749890489}, {"source": 18, "isCrit": false, "target": 6, "similarity": 0.951492129399596}, {"source": 18, "isCrit": false, "target": 114, "similarity": 0.94900699118651}, {"source": 18, "isCrit": true, "target": 26, "similarity": 0.93996130879842}, {"source": 18, "isCrit": true, "target": 75, "similarity": 0.929549176565272}, {"source": 18, "isCrit": true, "target": 47, "similarity": 0.891132296536834}, {"source": 113, "isCrit": true, "target": 109, "similarity": 0.964938683469049}, {"source": 113, "isCrit": false, "target": 37, "similarity": 0.964860075150642}, {"source": 113, "isCrit": false, "target": 54, "similarity": 0.962551750962348}, {"source": 113, "isCrit": false, "target": 115, "similarity": 0.962431915075024}, {"source": 113, "isCrit": false, "target": 32, "similarity": 0.957441702246796}, {"source": 15, "isCrit": true, "target": 85, "similarity": 0.956118791508499}, {"source": 15, "isCrit": false, "target": 62, "similarity": 0.955433288298729}, {"source": 15, "isCrit": false, "target": 65, "similarity": 0.94915087883083}, {"source": 15, "isCrit": true, "target": 58, "similarity": 0.949126843360407}, {"source": 15, "isCrit": false, "target": 63, "similarity": 0.946228166848935}, {"source": 5, "isCrit": true, "target": 105, "similarity": 0.953044754257555}, {"source": 5, "isCrit": false, "target": 107, "similarity": 0.944455916877679}, {"source": 5, "isCrit": false, "target": 0, "similarity": 0.935973198834059}, {"source": 5, "isCrit": false, "target": 67, "similarity": 0.93273370698117}, {"source": 5, "isCrit": false, "target": 17, "similarity": 0.931774408894087}, {"source": 79, "isCrit": true, "target": 9, "similarity": 0.956741955743287}, {"source": 79, "isCrit": false, "target": 0, "similarity": 0.956618281947693}, {"source": 79, "isCrit": false, "target": 102, "similarity": 0.95610808365048}, {"source": 79, "isCrit": false, "target": 1, "similarity": 0.95221521418508}, {"source": 79, "isCrit": false, "target": 71, "similarity": 0.945878389406814}, {"source": 126, "isCrit": true, "target": 78, "similarity": 0.951402113161974}, {"source": 126, "isCrit": false, "target": 110, "similarity": 0.947902384564773}, {"source": 126, "isCrit": false, "target": 33, "similarity": 0.9460618029303}, {"source": 126, "isCrit": false, "target": 1, "similarity": 0.945250150131411}, {"source": 126, "isCrit": false, "target": 0, "similarity": 0.945055455536308}, {"source": 33, "isCrit": true, "target": 121, "similarity": 0.986326048210577}, {"source": 33, "isCrit": true, "target": 78, "similarity": 0.977938657746959}, {"source": 33, "isCrit": false, "target": 0, "similarity": 0.972029247163155}, {"source": 33, "isCrit": false, "target": 1, "similarity": 0.971504228453823}, {"source": 33, "isCrit": true, "target": 55, "similarity": 0.968294727752109}, {"source": 33, "isCrit": true, "target": 101, "similarity": 0.958684171189161}, {"source": 33, "isCrit": true, "target": 3, "similarity": 0.951709308069246}, {"source": 33, "isCrit": true, "target": 13, "similarity": 0.943596769667802}, {"source": 33, "isCrit": true, "target": 57, "similarity": 0.906298862482613}, {"source": 2, "isCrit": true, "target": 37, "similarity": 0.951588483421979}, {"source": 2, "isCrit": false, "target": 32, "similarity": 0.949098498818862}, {"source": 2, "isCrit": false, "target": 61, "similarity": 0.948488354370915}, {"source": 2, "isCrit": false, "target": 45, "similarity": 0.948481733304462}, {"source": 2, "isCrit": false, "target": 115, "similarity": 0.944623009194731}, {"source": 37, "isCrit": true, "target": 115, "similarity": 0.993250826175802}, {"source": 37, "isCrit": true, "target": 32, "similarity": 0.992654293917992}, {"source": 37, "isCrit": true, "target": 84, "similarity": 0.989695015811754}, {"source": 37, "isCrit": true, "target": 54, "similarity": 0.985818850439507}, {"source": 37, "isCrit": false, "target": 49, "similarity": 0.983734392757487}, {"source": 37, "isCrit": true, "target": 45, "similarity": 0.981976963085237}, {"source": 37, "isCrit": true, "target": 53, "similarity": 0.979430208453645}, {"source": 37, "isCrit": true, "target": 103, "similarity": 0.979342262903173}, {"source": 37, "isCrit": true, "target": 22, "similarity": 0.978317558369276}, {"source": 37, "isCrit": true, "target": 11, "similarity": 0.974828646533121}, {"source": 37, "isCrit": true, "target": 69, "similarity": 0.972049530097492}, {"source": 37, "isCrit": true, "target": 82, "similarity": 0.971187782496251}, {"source": 37, "isCrit": true, "target": 125, "similarity": 0.969501993486321}, {"source": 37, "isCrit": true, "target": 139, "similarity": 0.966105243827405}, {"source": 37, "isCrit": true, "target": 132, "similarity": 0.953780450270283}, {"source": 37, "isCrit": true, "target": 2, "similarity": 0.951588483421979}, {"source": 84, "isCrit": true, "target": 37, "similarity": 0.989695015811754}, {"source": 84, "isCrit": false, "target": 32, "similarity": 0.985918080908192}, {"source": 84, "isCrit": true, "target": 127, "similarity": 0.98392097435455}, {"source": 84, "isCrit": false, "target": 115, "similarity": 0.983310822192201}, {"source": 84, "isCrit": false, "target": 29, "similarity": 0.982246010570176}, {"source": 84, "isCrit": true, "target": 111, "similarity": 0.979031461968329}, {"source": 84, "isCrit": true, "target": 94, "similarity": 0.937830218431544}, {"source": 25, "isCrit": true, "target": 101, "similarity": 0.981991227397148}, {"source": 25, "isCrit": false, "target": 29, "similarity": 0.981286324193724}, {"source": 25, "isCrit": false, "target": 36, "similarity": 0.981067959522196}, {"source": 25, "isCrit": false, "target": 97, "similarity": 0.981034655980989}, {"source": 25, "isCrit": false, "target": 84, "similarity": 0.978602041265347}, {"source": 25, "isCrit": true, "target": 120, "similarity": 0.976660689429397}, {"source": 25, "isCrit": true, "target": 46, "similarity": 0.973752647641024}, {"source": 25, "isCrit": true, "target": 108, "similarity": 0.96839220868351}, {"source": 70, "isCrit": true, "target": 1, "similarity": 0.947026133420038}, {"source": 70, "isCrit": false, "target": 9, "similarity": 0.946690563987305}, {"source": 70, "isCrit": false, "target": 71, "similarity": 0.940205819823557}, {"source": 70, "isCrit": false, "target": 0, "similarity": 0.938504163269229}, {"source": 70, "isCrit": false, "target": 79, "similarity": 0.937022259502795}, {"source": 61, "isCrit": true, "target": 97, "similarity": 0.977978846747355}, {"source": 61, "isCrit": false, "target": 32, "similarity": 0.976988708380221}, {"source": 61, "isCrit": true, "target": 66, "similarity": 0.975746962390426}, {"source": 61, "isCrit": false, "target": 101, "similarity": 0.975148593742063}, {"source": 61, "isCrit": false, "target": 29, "similarity": 0.974883399485059}, {"source": 61, "isCrit": true, "target": 135, "similarity": 0.955380672134195}, {"source": 61, "isCrit": true, "target": 137, "similarity": 0.930475364011393}, {"source": 101, "isCrit": true, "target": 36, "similarity": 0.986008503352287}, {"source": 101, "isCrit": true, "target": 97, "similarity": 0.984762590299216}, {"source": 101, "isCrit": true, "target": 29, "similarity": 0.983651129514385}, {"source": 101, "isCrit": true, "target": 25, "similarity": 0.981991227397148}, {"source": 101, "isCrit": false, "target": 56, "similarity": 0.979234507764399}, {"source": 101, "isCrit": true, "target": 33, "similarity": 0.958684171189161}, {"source": 69, "isCrit": true, "target": 37, "similarity": 0.972049530097492}, {"source": 69, "isCrit": false, "target": 109, "similarity": 0.968228243694358}, {"source": 69, "isCrit": false, "target": 115, "similarity": 0.967167999339114}, {"source": 69, "isCrit": false, "target": 32, "similarity": 0.964215648178443}, {"source": 69, "isCrit": false, "target": 49, "similarity": 0.96344828411526}, {"source": 95, "isCrit": true, "target": 56, "similarity": 0.95552601092894}, {"source": 95, "isCrit": false, "target": 101, "similarity": 0.952902247702835}, {"source": 95, "isCrit": false, "target": 97, "similarity": 0.952274373143925}, {"source": 95, "isCrit": false, "target": 89, "similarity": 0.952222421851767}, {"source": 95, "isCrit": false, "target": 36, "similarity": 0.946272870506929}, {"source": 6, "isCrit": true, "target": 76, "similarity": 0.985758572290652}, {"source": 6, "isCrit": true, "target": 31, "similarity": 0.985441206284586}, {"source": 6, "isCrit": true, "target": 72, "similarity": 0.979972769626164}, {"source": 6, "isCrit": false, "target": 65, "similarity": 0.976290364645985}, {"source": 6, "isCrit": true, "target": 99, "similarity": 0.96851466261862}, {"source": 6, "isCrit": true, "target": 16, "similarity": 0.966211057543427}, {"source": 6, "isCrit": true, "target": 81, "similarity": 0.952593874319656}, {"source": 6, "isCrit": true, "target": 116, "similarity": 0.95044402380081}, {"source": 6, "isCrit": true, "target": 27, "similarity": 0.94459431509334}, {"source": 6, "isCrit": true, "target": 98, "similarity": 0.93842362611799}, {"source": 6, "isCrit": true, "target": 10, "similarity": 0.927092596551579}, {"source": 6, "isCrit": true, "target": 74, "similarity": 0.903353016025231}, {"source": 40, "isCrit": true, "target": 65, "similarity": 0.958082238938593}, {"source": 40, "isCrit": false, "target": 76, "similarity": 0.957885418053363}, {"source": 40, "isCrit": false, "target": 6, "similarity": 0.955702444872786}, {"source": 40, "isCrit": false, "target": 85, "similarity": 0.952203947468211}, {"source": 40, "isCrit": false, "target": 62, "similarity": 0.949314769493467}, {"source": 40, "isCrit": true, "target": 77, "similarity": 0.924980223507533}, {"source": 40, "isCrit": true, "target": 19, "similarity": 0.915380918141528}, {"source": 12, "isCrit": true, "target": 76, "similarity": 0.956849175454137}, {"source": 12, "isCrit": false, "target": 65, "similarity": 0.95668970654998}, {"source": 12, "isCrit": false, "target": 87, "similarity": 0.951012304833263}, {"source": 12, "isCrit": false, "target": 62, "similarity": 0.949187443798135}, {"source": 12, "isCrit": false, "target": 51, "similarity": 0.940873145574154}, {"source": 92, "isCrit": true, "target": 1, "similarity": 0.972251478243341}, {"source": 92, "isCrit": false, "target": 78, "similarity": 0.970519127019891}, {"source": 92, "isCrit": false, "target": 71, "similarity": 0.96476909327931}, {"source": 92, "isCrit": false, "target": 0, "similarity": 0.964213471702732}, {"source": 92, "isCrit": false, "target": 9, "similarity": 0.961817692939318}, {"source": 29, "isCrit": true, "target": 101, "similarity": 0.983651129514385}, {"source": 29, "isCrit": true, "target": 32, "similarity": 0.983555280609945}, {"source": 29, "isCrit": false, "target": 97, "similarity": 0.983239376035887}, {"source": 29, "isCrit": false, "target": 36, "similarity": 0.982428923603105}, {"source": 29, "isCrit": false, "target": 84, "similarity": 0.982246010570176}, {"source": 29, "isCrit": true, "target": 8, "similarity": 0.935976038639453}, {"source": 41, "isCrit": true, "target": 11, "similarity": 0.948458786654429}, {"source": 41, "isCrit": false, "target": 25, "similarity": 0.946820111343317}, {"source": 41, "isCrit": false, "target": 54, "similarity": 0.94676121097248}, {"source": 41, "isCrit": false, "target": 37, "similarity": 0.946198984281526}, {"source": 41, "isCrit": false, "target": 32, "similarity": 0.945831285996104}, {"source": 36, "isCrit": true, "target": 101, "similarity": 0.986008503352287}, {"source": 36, "isCrit": false, "target": 97, "similarity": 0.984548628323379}, {"source": 36, "isCrit": false, "target": 29, "similarity": 0.982428923603105}, {"source": 36, "isCrit": false, "target": 56, "similarity": 0.981486538977206}, {"source": 36, "isCrit": false, "target": 25, "similarity": 0.981067959522196}, {"source": 36, "isCrit": true, "target": 7, "similarity": 0.973369231899439}, {"source": 36, "isCrit": true, "target": 112, "similarity": 0.947316502075678}, {"source": 46, "isCrit": true, "target": 25, "similarity": 0.973752647641024}, {"source": 46, "isCrit": false, "target": 36, "similarity": 0.969277679445036}, {"source": 46, "isCrit": false, "target": 101, "similarity": 0.968961344500706}, {"source": 46, "isCrit": false, "target": 97, "similarity": 0.967698642994529}, {"source": 46, "isCrit": false, "target": 29, "similarity": 0.966550768066719}, {"source": 115, "isCrit": true, "target": 37, "similarity": 0.993250826175802}, {"source": 115, "isCrit": false, "target": 32, "similarity": 0.98588285437695}, {"source": 115, "isCrit": true, "target": 49, "similarity": 0.985192120487506}, {"source": 115, "isCrit": false, "target": 84, "similarity": 0.983310822192201}, {"source": 115, "isCrit": false, "target": 54, "similarity": 0.981876266590097}, {"source": 136, "isCrit": true, "target": 78, "similarity": 0.972408298518613}, {"source": 136, "isCrit": false, "target": 1, "similarity": 0.968747416817857}, {"source": 136, "isCrit": false, "target": 33, "similarity": 0.963776108796743}, {"source": 136, "isCrit": true, "target": 59, "similarity": 0.960598507585344}, {"source": 136, "isCrit": false, "target": 9, "similarity": 0.956514168000029}, {"source": 55, "isCrit": true, "target": 33, "similarity": 0.968294727752109}, {"source": 55, "isCrit": false, "target": 121, "similarity": 0.960756147598928}, {"source": 55, "isCrit": false, "target": 78, "similarity": 0.959956173069116}, {"source": 55, "isCrit": false, "target": 0, "similarity": 0.959526471463833}, {"source": 55, "isCrit": false, "target": 9, "similarity": 0.958096777442152}, {"source": 55, "isCrit": true, "target": 123, "similarity": 0.935886602143994}, {"source": 121, "isCrit": true, "target": 33, "similarity": 0.986326048210577}, {"source": 121, "isCrit": false, "target": 0, "similarity": 0.97334793190948}, {"source": 121, "isCrit": false, "target": 78, "similarity": 0.964956282952852}, {"source": 121, "isCrit": false, "target": 1, "similarity": 0.96409357168642}, {"source": 121, "isCrit": false, "target": 9, "similarity": 0.962233925515866}, {"source": 53, "isCrit": true, "target": 37, "similarity": 0.979430208453645}, {"source": 53, "isCrit": false, "target": 115, "similarity": 0.975669934672246}, {"source": 53, "isCrit": false, "target": 32, "similarity": 0.973836223954786}, {"source": 53, "isCrit": false, "target": 84, "similarity": 0.972053412261723}, {"source": 53, "isCrit": false, "target": 45, "similarity": 0.971920801042056}, {"source": 111, "isCrit": true, "target": 84, "similarity": 0.979031461968329}, {"source": 111, "isCrit": false, "target": 29, "similarity": 0.978819142501638}, {"source": 111, "isCrit": false, "target": 127, "similarity": 0.975544135673836}, {"source": 111, "isCrit": false, "target": 97, "similarity": 0.974725639096156}, {"source": 111, "isCrit": false, "target": 101, "similarity": 0.973920697452188}, {"source": 110, "isCrit": true, "target": 78, "similarity": 0.951600517692281}, {"source": 110, "isCrit": false, "target": 3, "similarity": 0.949220622383177}, {"source": 110, "isCrit": false, "target": 136, "similarity": 0.94855016141627}, {"source": 110, "isCrit": false, "target": 126, "similarity": 0.947902384564773}, {"source": 110, "isCrit": false, "target": 118, "similarity": 0.947277782425834}, {"source": 72, "isCrit": true, "target": 6, "similarity": 0.979972769626164}, {"source": 72, "isCrit": false, "target": 76, "similarity": 0.973564798399153}, {"source": 72, "isCrit": false, "target": 65, "similarity": 0.969548661866613}, {"source": 72, "isCrit": false, "target": 31, "similarity": 0.969292429912344}, {"source": 72, "isCrit": false, "target": 85, "similarity": 0.963151846244236}, {"source": 72, "isCrit": true, "target": 18, "similarity": 0.960700512271495}, {"source": 72, "isCrit": true, "target": 91, "similarity": 0.960077548173284}, {"source": 72, "isCrit": true, "target": 106, "similarity": 0.958896599747964}, {"source": 72, "isCrit": true, "target": 128, "similarity": 0.952830999631805}, {"source": 72, "isCrit": true, "target": 42, "similarity": 0.945800614958682}, {"source": 72, "isCrit": true, "target": 68, "similarity": 0.945740899264155}, {"source": 72, "isCrit": true, "target": 109, "similarity": 0.941711689006963}, {"source": 72, "isCrit": true, "target": 130, "similarity": 0.939566613981911}, {"source": 72, "isCrit": true, "target": 122, "similarity": 0.922992153354024}, {"source": 72, "isCrit": true, "target": 96, "similarity": 0.921954829539572}, {"source": 72, "isCrit": true, "target": 24, "similarity": 0.920429950720939}, {"source": 28, "isCrit": true, "target": 56, "similarity": 0.979536401031809}, {"source": 28, "isCrit": false, "target": 89, "similarity": 0.978532869928923}, {"source": 28, "isCrit": false, "target": 36, "similarity": 0.976616347474291}, {"source": 28, "isCrit": false, "target": 97, "similarity": 0.973202803759583}, {"source": 28, "isCrit": false, "target": 101, "similarity": 0.971647695576584}, {"source": 67, "isCrit": true, "target": 71, "similarity": 0.975257046608221}, {"source": 67, "isCrit": false, "target": 9, "similarity": 0.969973649478448}, {"source": 67, "isCrit": false, "target": 107, "similarity": 0.964829058538292}, {"source": 67, "isCrit": false, "target": 1, "similarity": 0.963159703766021}, {"source": 67, "isCrit": false, "target": 92, "similarity": 0.960612078314065}, {"source": 134, "isCrit": true, "target": 105, "similarity": 0.969288593921551}, {"source": 134, "isCrit": false, "target": 17, "similarity": 0.952707416520116}, {"source": 134, "isCrit": false, "target": 89, "similarity": 0.949626780640545}, {"source": 134, "isCrit": false, "target": 28, "similarity": 0.949143527918306}, {"source": 134, "isCrit": true, "target": 50, "similarity": 0.94650843864418}, {"source": 97, "isCrit": true, "target": 101, "similarity": 0.984762590299216}, {"source": 97, "isCrit": false, "target": 36, "similarity": 0.984548628323379}, {"source": 97, "isCrit": false, "target": 29, "similarity": 0.983239376035887}, {"source": 97, "isCrit": true, "target": 56, "similarity": 0.982442708308227}, {"source": 97, "isCrit": false, "target": 25, "similarity": 0.981034655980989}, {"source": 97, "isCrit": true, "target": 60, "similarity": 0.979413729124948}, {"source": 97, "isCrit": true, "target": 61, "similarity": 0.977978846747355}, {"source": 97, "isCrit": true, "target": 23, "similarity": 0.969785729085341}, {"source": 97, "isCrit": true, "target": 104, "similarity": 0.920775157717401}, {"source": 51, "isCrit": true, "target": 76, "similarity": 0.962875863443947}, {"source": 51, "isCrit": false, "target": 65, "similarity": 0.957474106885003}, {"source": 51, "isCrit": false, "target": 6, "similarity": 0.952948745455536}, {"source": 51, "isCrit": false, "target": 31, "similarity": 0.949890052304694}, {"source": 51, "isCrit": false, "target": 87, "similarity": 0.949509798947515}, {"source": 14, "isCrit": true, "target": 65, "similarity": 0.900684313336204}, {"source": 14, "isCrit": false, "target": 76, "similarity": 0.89881940029389}, {"source": 14, "isCrit": false, "target": 85, "similarity": 0.898718084017108}, {"source": 14, "isCrit": false, "target": 6, "similarity": 0.894039315196773}, {"source": 14, "isCrit": false, "target": 72, "similarity": 0.89248134280619}, {"source": 129, "isCrit": true, "target": 44, "similarity": 0.967578877863936}, {"source": 129, "isCrit": false, "target": 97, "similarity": 0.961259505880446}, {"source": 129, "isCrit": false, "target": 66, "similarity": 0.959046106035003}, {"source": 129, "isCrit": false, "target": 61, "similarity": 0.956279151333369}, {"source": 129, "isCrit": false, "target": 28, "similarity": 0.9544561806107}, {"source": 34, "isCrit": true, "target": 17, "similarity": 0.925615888828337}, {"source": 34, "isCrit": false, "target": 55, "similarity": 0.92207585342125}, {"source": 34, "isCrit": false, "target": 121, "similarity": 0.920265360443099}, {"source": 34, "isCrit": false, "target": 33, "similarity": 0.91773716180859}, {"source": 34, "isCrit": false, "target": 0, "similarity": 0.912732989420008}, {"source": 99, "isCrit": true, "target": 6, "similarity": 0.96851466261862}, {"source": 99, "isCrit": false, "target": 31, "similarity": 0.965330143638736}, {"source": 99, "isCrit": false, "target": 76, "similarity": 0.961428927847895}, {"source": 99, "isCrit": false, "target": 72, "similarity": 0.958604085360301}, {"source": 99, "isCrit": false, "target": 65, "similarity": 0.954407899112757}, {"source": 82, "isCrit": true, "target": 37, "similarity": 0.971187782496251}, {"source": 82, "isCrit": false, "target": 32, "similarity": 0.968801061526069}, {"source": 82, "isCrit": false, "target": 115, "similarity": 0.967326835441665}, {"source": 82, "isCrit": false, "target": 84, "similarity": 0.967120076212156}, {"source": 82, "isCrit": false, "target": 54, "similarity": 0.965890860219264}, {"source": 9, "isCrit": true, "target": 71, "similarity": 0.979201061894335}, {"source": 9, "isCrit": true, "target": 1, "similarity": 0.97552847716641}, {"source": 9, "isCrit": true, "target": 118, "similarity": 0.974638634288806}, {"source": 9, "isCrit": true, "target": 0, "similarity": 0.973931901054439}, {"source": 9, "isCrit": false, "target": 67, "similarity": 0.969973649478448}, {"source": 9, "isCrit": true, "target": 21, "similarity": 0.966995571083706}, {"source": 9, "isCrit": true, "target": 102, "similarity": 0.965383954797223}, {"source": 9, "isCrit": true, "target": 133, "similarity": 0.959890591263}, {"source": 9, "isCrit": true, "target": 88, "similarity": 0.95765594470018}, {"source": 9, "isCrit": true, "target": 79, "similarity": 0.956741955743287}, {"source": 9, "isCrit": true, "target": 86, "similarity": 0.950489724839737}, {"source": 9, "isCrit": true, "target": 38, "similarity": 0.947517759604886}, {"source": 9, "isCrit": true, "target": 48, "similarity": 0.942936216503977}, {"source": 9, "isCrit": true, "target": 80, "similarity": 0.939537560472174}, {"source": 9, "isCrit": true, "target": 117, "similarity": 0.937466287042329}, {"source": 9, "isCrit": true, "target": 35, "similarity": 0.906837924100564}, {"source": 4, "isCrit": true, "target": 76, "similarity": 0.905743615338944}, {"source": 4, "isCrit": false, "target": 65, "similarity": 0.901050432939524}, {"source": 4, "isCrit": false, "target": 6, "similarity": 0.899400562040688}, {"source": 4, "isCrit": false, "target": 31, "similarity": 0.896812995657916}, {"source": 4, "isCrit": false, "target": 119, "similarity": 0.89437579338554}, {"source": 50, "isCrit": true, "target": 134, "similarity": 0.94650843864418}, {"source": 50, "isCrit": false, "target": 105, "similarity": 0.940781714689728}, {"source": 50, "isCrit": false, "target": 17, "similarity": 0.936169513638403}, {"source": 50, "isCrit": false, "target": 0, "similarity": 0.93493596915569}, {"source": 50, "isCrit": false, "target": 28, "similarity": 0.925648078243575}, {"source": 23, "isCrit": true, "target": 97, "similarity": 0.969785729085341}, {"source": 23, "isCrit": false, "target": 25, "similarity": 0.967406579743062}, {"source": 23, "isCrit": false, "target": 101, "similarity": 0.966730673398781}, {"source": 23, "isCrit": false, "target": 36, "similarity": 0.964641524759787}, {"source": 23, "isCrit": false, "target": 29, "similarity": 0.963200311624761}, {"source": 77, "isCrit": true, "target": 40, "similarity": 0.924980223507533}, {"source": 77, "isCrit": false, "target": 6, "similarity": 0.917302845698064}, {"source": 77, "isCrit": false, "target": 85, "similarity": 0.915918950108495}, {"source": 77, "isCrit": false, "target": 76, "similarity": 0.915257517334061}, {"source": 77, "isCrit": false, "target": 65, "similarity": 0.914976783667773}, {"source": 112, "isCrit": true, "target": 36, "similarity": 0.947316502075678}, {"source": 112, "isCrit": false, "target": 25, "similarity": 0.945587247466868}, {"source": 112, "isCrit": false, "target": 29, "similarity": 0.943749808390193}, {"source": 112, "isCrit": false, "target": 101, "similarity": 0.94061409817848}, {"source": 112, "isCrit": false, "target": 120, "similarity": 0.940336629692104}, {"source": 133, "isCrit": true, "target": 9, "similarity": 0.959890591263}, {"source": 133, "isCrit": false, "target": 1, "similarity": 0.959602581701441}, {"source": 133, "isCrit": false, "target": 0, "similarity": 0.958578325294204}, {"source": 133, "isCrit": false, "target": 107, "similarity": 0.956581577554007}, {"source": 133, "isCrit": false, "target": 102, "similarity": 0.956033001212097}, {"source": 131, "isCrit": true, "target": 1, "similarity": 0.967096598063328}, {"source": 131, "isCrit": false, "target": 78, "similarity": 0.96708636829244}, {"source": 131, "isCrit": false, "target": 33, "similarity": 0.966978448014816}, {"source": 131, "isCrit": false, "target": 0, "similarity": 0.9668593593283}, {"source": 131, "isCrit": false, "target": 71, "similarity": 0.960138571918042}, {"source": 78, "isCrit": true, "target": 33, "similarity": 0.977938657746959}, {"source": 78, "isCrit": true, "target": 1, "similarity": 0.97765122862698}, {"source": 78, "isCrit": true, "target": 136, "similarity": 0.972408298518613}, {"source": 78, "isCrit": false, "target": 92, "similarity": 0.970519127019891}, {"source": 78, "isCrit": false, "target": 9, "similarity": 0.968720842843539}, {"source": 78, "isCrit": true, "target": 64, "similarity": 0.953555913001863}, {"source": 78, "isCrit": true, "target": 110, "similarity": 0.951600517692281}, {"source": 78, "isCrit": true, "target": 126, "similarity": 0.951402113161974}, {"source": 64, "isCrit": true, "target": 78, "similarity": 0.953555913001863}, {"source": 64, "isCrit": false, "target": 33, "similarity": 0.951298038891614}, {"source": 64, "isCrit": false, "target": 1, "similarity": 0.942732933739747}, {"source": 64, "isCrit": false, "target": 92, "similarity": 0.938724850136189}, {"source": 64, "isCrit": false, "target": 136, "similarity": 0.937798820096026}, {"source": 24, "isCrit": true, "target": 72, "similarity": 0.920429950720939}, {"source": 24, "isCrit": false, "target": 128, "similarity": 0.919207121883588}, {"source": 24, "isCrit": false, "target": 18, "similarity": 0.918068895626406}, {"source": 24, "isCrit": false, "target": 130, "similarity": 0.916610933429015}, {"source": 24, "isCrit": false, "target": 85, "similarity": 0.914628764331305}, {"source": 132, "isCrit": true, "target": 37, "similarity": 0.953780450270283}, {"source": 132, "isCrit": false, "target": 32, "similarity": 0.952018696562842}, {"source": 132, "isCrit": false, "target": 84, "similarity": 0.951338842208283}, {"source": 132, "isCrit": false, "target": 127, "similarity": 0.950600745596262}, {"source": 132, "isCrit": false, "target": 115, "similarity": 0.949611047052216}, {"source": 27, "isCrit": true, "target": 6, "similarity": 0.94459431509334}, {"source": 27, "isCrit": false, "target": 72, "similarity": 0.942243148928001}, {"source": 27, "isCrit": false, "target": 65, "similarity": 0.941283247022078}, {"source": 27, "isCrit": false, "target": 76, "similarity": 0.940107155519373}, {"source": 27, "isCrit": false, "target": 99, "similarity": 0.938446422324324}, {"source": 85, "isCrit": true, "target": 65, "similarity": 0.972842994747225}, {"source": 85, "isCrit": false, "target": 76, "similarity": 0.972753603177933}, {"source": 85, "isCrit": true, "target": 62, "similarity": 0.970570763674631}, {"source": 85, "isCrit": false, "target": 72, "similarity": 0.963151846244236}, {"source": 85, "isCrit": false, "target": 6, "similarity": 0.961428319342822}, {"source": 85, "isCrit": true, "target": 15, "similarity": 0.956118791508499}, {"source": 130, "isCrit": true, "target": 72, "similarity": 0.939566613981911}, {"source": 130, "isCrit": false, "target": 18, "similarity": 0.938615488242119}, {"source": 130, "isCrit": false, "target": 6, "similarity": 0.930701526501176}, {"source": 130, "isCrit": false, "target": 128, "similarity": 0.927054770899124}, {"source": 130, "isCrit": false, "target": 75, "similarity": 0.925456541440587}, {"source": 88, "isCrit": true, "target": 9, "similarity": 0.95765594470018}, {"source": 88, "isCrit": false, "target": 71, "similarity": 0.955826889191775}, {"source": 88, "isCrit": false, "target": 107, "similarity": 0.954605398933203}, {"source": 88, "isCrit": false, "target": 1, "similarity": 0.953146889304982}, {"source": 88, "isCrit": false, "target": 78, "similarity": 0.952942932331791}, {"source": 16, "isCrit": true, "target": 6, "similarity": 0.966211057543427}, {"source": 16, "isCrit": false, "target": 76, "similarity": 0.963132406234732}, {"source": 16, "isCrit": false, "target": 72, "similarity": 0.960382466050291}, {"source": 16, "isCrit": false, "target": 31, "similarity": 0.958286500531145}, {"source": 16, "isCrit": false, "target": 65, "similarity": 0.957789324182343}, {"source": 35, "isCrit": true, "target": 9, "similarity": 0.906837924100564}, {"source": 35, "isCrit": false, "target": 131, "similarity": 0.905971616627396}, {"source": 35, "isCrit": false, "target": 0, "similarity": 0.905391173803852}, {"source": 35, "isCrit": false, "target": 107, "similarity": 0.902334711342221}, {"source": 35, "isCrit": false, "target": 105, "similarity": 0.9012517070126}]}